{
  "checksums": [
    {
      "id": "github_content/github.com/awslabs/git-secrets/1.3.0/git-secrets",
      "checksum": "DF9A5D2BEEDA1C83E23105F46EFE464BB4C97F8328E1E66754D7DAACFAF7272B",
      "algorithm": "sha256"
    },
    {
      "id": "github_release/github.com/BurntSushi/ripgrep/14.1.1/ripgrep-14.1.1-aarch64-apple-darwin.tar.gz",
      "checksum": "24AD76777745FBFF131C8FBC466742B011F925BFA4FFFA2DED6DEF23B5B937BE",
      "algorithm": "sha256"
    },
    {
      "id": "github_release/github.com/BurntSushi/ripgrep/14.1.1/ripgrep-14.1.1-aarch64-unknown-linux-gnu.tar.gz",
      "checksum": "C827481C4FF4EA10C9DC7A4022C8DE5DB34A5737CB74484D62EB94A95841AB2F",
      "algorithm": "sha256"
    },
    {
      "id": "github_release/github.com/BurntSushi/ripgrep/14.1.1/ripgrep-14.1.1-x86_64-apple-darwin.tar.gz",
      "checksum": "FC87E78F7CB3FEA12D69072E7EF3B21509754717B746368FD40D88963630E2B3",
      "algorithm": "sha256"
    },
    {
      "id": "github_release/github.com/BurntSushi/ripgrep/14.1.1/ripgrep-14.1.1-x86_64-pc-windows-msvc.zip",
      "checksum": "D0F534024C42AFD6CB4D38907C25CD2B249B79BBE6CC1DBEE8E3E37C2B6E25A1",
      "algorithm": "sha256"
    },
    {
      "id": "github_release/github.com/BurntSushi/ripgrep/14.1.1/ripgrep-14.1.1-x86_64-unknown-linux-musl.tar.gz",
      "checksum": "4CF9F2741E6C465FFDB7C26F38056A59E2A2544B51F7CC128EF28337EEAE4D8E",
      "algorithm": "sha256"
    },
    {
      "id": "github_release/github.com/JohnnyMorganz/StyLua/v2.3.0/stylua-linux-aarch64.zip",
      "checksum": "A0874C81A2FDB5C7507B1280E02E0F5012322558328859C746348CA2304B436A",
      "algorithm": "sha256"
    },
    {
      "id": "github_release/github.com/JohnnyMorganz/StyLua/v2.3.0/stylua-linux-x86_64-musl.zip",
      "checksum": "E087BCC9AA0F7D17567666EA429B1A7D0FCEEFFBAF78C98105913D0FC48D7744",
      "algorithm": "sha256"
    },
    {
      "id": "github_release/github.com/JohnnyMorganz/StyLua/v2.3.0/stylua-macos-aarch64.zip",
      "checksum": "5C037DA91602317EE88846EF8EF001FDBB5C4DD9CF60E27318F67C6AE2C6B898",
      "algorithm": "sha256"
    },
    {
      "id": "github_release/github.com/JohnnyMorganz/StyLua/v2.3.0/stylua-macos-x86_64.zip",
      "checksum": "C0AD32EC909EDC37670D3BC5D72D80C3C18672F9D6D6F654D08A57CF5CA49ED4",
      "algorithm": "sha256"
    },
    {
      "id": "github_release/github.com/JohnnyMorganz/StyLua/v2.3.0/stylua-windows-x86_64.zip",
      "checksum": "9A825BDF78EE2C300C30BAF6CC7EABCFD4057D8680BDEE3546E8715B72DEF1D9",
      "algorithm": "sha256"
    },
    {
      "id": "github_release/github.com/LuaLS/lua-language-server/3.15.0/lua-language-server-3.15.0-darwin-arm64.tar.gz",
      "checksum": "050F5F493F65112AFC116E31281A9F73918546782D3696485DC052724838F58B",
      "algorithm": "sha256"
    },
    {
      "id": "github_release/github.com/LuaLS/lua-language-server/3.15.0/lua-language-server-3.15.0-darwin-x64.tar.gz",
      "checksum": "01D28A31E264434E51662814A68F584AF068393CAECFA158C4DF5F7FDC3CA2F7",
      "algorithm": "sha256"
    },
    {
      "id": "github_release/github.com/LuaLS/lua-language-server/3.15.0/lua-language-server-3.15.0-linux-arm64.tar.gz",
      "checksum": "7DFF8EDFED4F34CF6325FF384791287D95F9A8DD9615A5279C7C6AF81CF8C45D",
      "algorithm": "sha256"
    },
    {
      "id": "github_release/github.com/LuaLS/lua-language-server/3.15.0/lua-language-server-3.15.0-linux-x64.tar.gz",
      "checksum": "4877B874C52FB7587707898DA9026CC3A6C854D9BBAB115EF49AC4E6A1B88007",
      "algorithm": "sha256"
    },
    {
      "id": "github_release/github.com/LuaLS/lua-language-server/3.15.0/lua-language-server-3.15.0-win32-x64.zip",
      "checksum": "76A10C05E8C947A448F00A61ACEAD4240484CD1E2E8C66D54401C67D99B77535",
      "algorithm": "sha256"
    },
    {
      "id": "github_release/github.com/Schniz/fnm/v1.38.1/fnm-arm64.zip",
      "checksum": "69FEDA9455931C26C84BE9F95F5E6F69E8B64686E68069FAB7CFC34756CD2944",
      "algorithm": "sha256"
    },
    {
      "id": "github_release/github.com/Schniz/fnm/v1.38.1/fnm-linux.zip",
      "checksum": "B69E5C9A05C1E17E4A7DE9A17DF14BA430D049F2591AF791A6F850A170296069",
      "algorithm": "sha256"
    },
    {
      "id": "github_release/github.com/Schniz/fnm/v1.38.1/fnm-macos.zip",
      "checksum": "80DEB3DB3DB45598F25AEA594C10936A7658F70826104FE37E33B4072A5E11F9",
      "algorithm": "sha256"
    },
    {
      "id": "github_release/github.com/Schniz/fnm/v1.38.1/fnm-windows.zip",
      "checksum": "377796E8F2F51EB8B5DE8983974CAA8922B83C167197B68B33962775703AD4A0",
      "algorithm": "sha256"
    },
    {
      "id": "github_release/github.com/Wilfred/difftastic/0.65.0/difft-aarch64-apple-darwin.tar.gz",
      "checksum": "B5D565F9586519F7E91799C6E3752B7CACF6110DD855B4CF019816E63C7C7F5F",
      "algorithm": "sha256"
    },
    {
      "id": "github_release/github.com/Wilfred/difftastic/0.65.0/difft-aarch64-unknown-linux-gnu.tar.gz",
      "checksum": "7930428E178BE78370B32DCDF71405AD08DE1065864424141D1D19ECF80469B2",
      "algorithm": "sha256"
    },
    {
      "id": "github_release/github.com/Wilfred/difftastic/0.65.0/difft-x86_64-apple-darwin.tar.gz",
      "checksum": "69CF21CB0629C63DADA7229F6BFE7E91A809335299B25ED14ABEB1080547C692",
      "algorithm": "sha256"
    },
    {
      "id": "github_release/github.com/Wilfred/difftastic/0.65.0/difft-x86_64-pc-windows-msvc.zip",
      "checksum": "2C8382ECC453F905408728BF901AA98289306625FE1F4E37549E90936CBC9D11",
      "algorithm": "sha256"
    },
    {
      "id": "github_release/github.com/Wilfred/difftastic/0.65.0/difft-x86_64-unknown-linux-musl.tar.gz",
      "checksum": "F439A90CB3188BACB77E1EA2BFF636355A5377324C3421D3F2920E10022FD48C",
      "algorithm": "sha256"
    },
    {
      "id": "github_release/github.com/ajeetdsouza/zoxide/v0.9.8/zoxide-0.9.8-aarch64-apple-darwin.tar.gz",
      "checksum": "3D1EC4AF7F3D351629F500B432E6C735CAF3216AB3EAA76DBE8FFBC8F3006F5A",
      "algorithm": "sha256"
    },
    {
      "id": "github_release/github.com/ajeetdsouza/zoxide/v0.9.8/zoxide-0.9.8-aarch64-pc-windows-msvc.zip",
      "checksum": "F1FB82EB558A50C43F635ABFE438BC7EE1620A9970959739CB5E9FDDF675821C",
      "algorithm": "sha256"
    },
    {
      "id": "github_release/github.com/ajeetdsouza/zoxide/v0.9.8/zoxide-0.9.8-aarch64-unknown-linux-musl.tar.gz",
      "checksum": "078CC9CC8CEDB6C45EDB84C0F5BAD53518C610859C73BDB3009A52B89652C103",
      "algorithm": "sha256"
    },
    {
      "id": "github_release/github.com/ajeetdsouza/zoxide/v0.9.8/zoxide-0.9.8-x86_64-apple-darwin.tar.gz",
      "checksum": "CFA865FFD1BA87DF2962F40EBD80C366F1D2B484F0C05B6DA6B0104F50822F86",
      "algorithm": "sha256"
    },
    {
      "id": "github_release/github.com/ajeetdsouza/zoxide/v0.9.8/zoxide-0.9.8-x86_64-pc-windows-msvc.zip",
      "checksum": "15DBD23AE3D98E2A745D0E8E3F0292402F0A2269B47519B81A6E994BACA5DB2B",
      "algorithm": "sha256"
    },
    {
      "id": "github_release/github.com/ajeetdsouza/zoxide/v0.9.8/zoxide-0.9.8-x86_64-unknown-linux-musl.tar.gz",
      "checksum": "4092EE38AA1EFDE42E4EFB2F9C872DF5388198AACAE7F1A74E5EB5C3CC7F531C",
      "algorithm": "sha256"
    },
    {
      "id": "github_release/github.com/astral-sh/uv/0.8.22/uv-aarch64-apple-darwin.tar.gz",
      "checksum": "3F61099E261E449527141DBF125629FAB33AD696468C8C90CEBBAC40185A306C",
      "algorithm": "sha256"
    },
    {
      "id": "github_release/github.com/astral-sh/uv/0.8.22/uv-aarch64-unknown-linux-musl.tar.gz",
      "checksum": "3CB3C891F56891F0027F0287980014930B18875C9396C1D8A19D607B0A6049D9",
      "algorithm": "sha256"
    },
    {
      "id": "github_release/github.com/astral-sh/uv/0.8.22/uv-x86_64-apple-darwin.tar.gz",
      "checksum": "76638FDCFA91357858771551A1C88DE1F7C3B270B33AB1866F8A0618D9E442D8",
      "algorithm": "sha256"
    },
    {
      "id": "github_release/github.com/astral-sh/uv/0.8.22/uv-x86_64-pc-windows-msvc.zip",
      "checksum": "5049375AA2A5162F132B2C1CB992E25D42D47D934CAB8C174DBE6F60973DCC12",
      "algorithm": "sha256"
    },
    {
      "id": "github_release/github.com/astral-sh/uv/0.8.22/uv-x86_64-unknown-linux-musl.tar.gz",
      "checksum": "06B891EF144BD8390FECB150838F0FF8A34CCAEECF9D744D97945D02EC7389C0",
      "algorithm": "sha256"
    },
    {
      "id": "github_release/github.com/auth0/auth0-cli/v1.21.0/auth0-cli_1.21.0_Darwin_arm64.tar.gz",
      "checksum": "3BA32C12011E887A5D2CB633A774169DD1FF05C4F8DC4E00D8BBFB91B1169B3B",
      "algorithm": "sha256"
    },
    {
      "id": "github_release/github.com/auth0/auth0-cli/v1.21.0/auth0-cli_1.21.0_Darwin_x86_64.tar.gz",
      "checksum": "12D4C9606F442E60487098AE2E544A5AFB783321BE662ACCD01D03CCE6EB5AD3",
      "algorithm": "sha256"
    },
    {
      "id": "github_release/github.com/auth0/auth0-cli/v1.21.0/auth0-cli_1.21.0_Linux_arm64.tar.gz",
      "checksum": "15E040A856BC420751E956835D91E230AA297D96BAE3EFE25531CCF18F42FEE4",
      "algorithm": "sha256"
    },
    {
      "id": "github_release/github.com/auth0/auth0-cli/v1.21.0/auth0-cli_1.21.0_Linux_x86_64.tar.gz",
      "checksum": "27E1FCC95D8054D8CBF4C14DC2D34E3B814690EA5C85EEA0A541E300F6363761",
      "algorithm": "sha256"
    },
    {
      "id": "github_release/github.com/auth0/auth0-cli/v1.21.0/auth0-cli_1.21.0_Windows_arm64.zip",
      "checksum": "CAFF7E5B876B05EE0FDDC0857716A75C0655F518D681BA52DEC6BE4575D5EEED",
      "algorithm": "sha256"
    },
    {
      "id": "github_release/github.com/auth0/auth0-cli/v1.21.0/auth0-cli_1.21.0_Windows_x86_64.zip",
      "checksum": "217121E83A8113F082B3745BA6771D2D8C617CEBABAA72BF54F428D6867C5714",
      "algorithm": "sha256"
    },
    {
      "id": "github_release/github.com/bufbuild/buf/v1.57.2/buf-Darwin-arm64.tar.gz",
      "checksum": "942DD3C96444615DEF14ED791DE33C882F9A6A2166EAD1C22973C04A4D3B186E",
      "algorithm": "sha256"
    },
    {
      "id": "github_release/github.com/bufbuild/buf/v1.57.2/buf-Darwin-x86_64.tar.gz",
      "checksum": "B5CEFC5EEC24331E26A49DB2B71B46E7E5A30D8D8F361F9CCC69E7DD5FDA5C7C",
      "algorithm": "sha256"
    },
    {
      "id": "github_release/github.com/bufbuild/buf/v1.57.2/buf-Linux-aarch64.tar.gz",
      "checksum": "FCC74BA98842BF431F2C4B9FCCC5FE77B13AAFD497125472AB341295F4915329",
      "algorithm": "sha256"
    },
    {
      "id": "github_release/github.com/bufbuild/buf/v1.57.2/buf-Linux-x86_64.tar.gz",
      "checksum": "275883A9BB684D37B26A5C86466870A3ACD2420163AC6F4827491498D89E34AD",
      "algorithm": "sha256"
    },
    {
      "id": "github_release/github.com/bufbuild/buf/v1.57.2/buf-Windows-arm64.exe",
      "checksum": "2B121609BC58181BE51CB057FD5621008DF92FBDFD31211ED1EE201137EF42DE",
      "algorithm": "sha256"
    },
    {
      "id": "github_release/github.com/bufbuild/buf/v1.57.2/buf-Windows-x86_64.exe",
      "checksum": "58C7A7E445C3FD4F14368A77436921C3B4577B42B7687C18CFB786D07CE3DF92",
      "algorithm": "sha256"
    },
    {
      "id": "github_release/github.com/cli/cli/v2.81.0/gh_2.81.0_linux_amd64.tar.gz",
      "checksum": "D507C82E3AE47AF875B93472F39E01CBF9F85808EC0A69751E0932A43514D7FF",
      "algorithm": "sha256"
    },
    {
      "id": "github_release/github.com/cli/cli/v2.81.0/gh_2.81.0_linux_arm64.tar.gz",
      "checksum": "766ADDA9877AFAF55F67626FF5D956BCEA84F1E5371DF5765BA30B1E786A86FD",
      "algorithm": "sha256"
    },
    {
      "id": "github_release/github.com/cli/cli/v2.81.0/gh_2.81.0_macOS_amd64.zip",
      "checksum": "C93BC9ADBAF768A2789B60360069BE8A623BEF94DF60AE5344F2B57AD8AE024F",
      "algorithm": "sha256"
    },
    {
      "id": "github_release/github.com/cli/cli/v2.81.0/gh_2.81.0_macOS_arm64.zip",
      "checksum": "B0F5A81601291123A25792859F7CA82229C1F1AE05B4B9F1A7E9E8BB63E649D5",
      "algorithm": "sha256"
    },
    {
      "id": "github_release/github.com/cli/cli/v2.81.0/gh_2.81.0_windows_amd64.zip",
      "checksum": "8F5A19EE2271D20477C5C8D8204B65CD0FF6D73279417F5CDAB49135516CA1B5",
      "algorithm": "sha256"
    },
    {
      "id": "github_release/github.com/cli/cli/v2.81.0/gh_2.81.0_windows_arm64.zip",
      "checksum": "8C95E5C9EE4FB907A7E096EE7959EE0A66D1EB44AD27380AFEC7219DAE65175B",
      "algorithm": "sha256"
    },
    {
      "id": "github_release/github.com/dandavison/delta/0.18.2/delta-0.18.2-aarch64-apple-darwin.tar.gz",
      "checksum": "6BA38DCE9F91EE1B9A24AA4AEDE1DB7195258FE176C3F8276AE2D4457D8170A0",
      "algorithm": "sha256"
    },
    {
      "id": "github_release/github.com/dandavison/delta/0.18.2/delta-0.18.2-aarch64-unknown-linux-gnu.tar.gz",
      "checksum": "ADF7674086DAA4582F598F74CE9CAA6B70C1BA8F4A57D2911499B37826B014F9",
      "algorithm": "sha256"
    },
    {
      "id": "github_release/github.com/dandavison/delta/0.18.2/delta-0.18.2-x86_64-apple-darwin.tar.gz",
      "checksum": "E9B5C4A9E73D2119C687E074F0D97F188E30E5FE8AE0E6D455755F74BB5CC0CF",
      "algorithm": "sha256"
    },
    {
      "id": "github_release/github.com/dandavison/delta/0.18.2/delta-0.18.2-x86_64-pc-windows-msvc.zip",
      "checksum": "6EA59864091B4CFCA89D9EE38388FF1A3CCDC8244B6E1CDD5201259DE89B0B06",
      "algorithm": "sha256"
    },
    {
      "id": "github_release/github.com/dandavison/delta/0.18.2/delta-0.18.2-x86_64-unknown-linux-musl.tar.gz",
      "checksum": "B7EA845004762358A00EF9127DD9FD723E333C7E4B9CB1DA220C3909372310EE",
      "algorithm": "sha256"
    },
    {
      "id": "github_release/github.com/denoland/deno/v2.5.2/deno-aarch64-apple-darwin.zip",
      "checksum": "1F6EE24F8273ACACDE8313E3F1EF615914DB7C9BB9427314E7C0B445B402AB98",
      "algorithm": "sha256"
    },
    {
      "id": "github_release/github.com/denoland/deno/v2.5.2/deno-aarch64-unknown-linux-gnu.zip",
      "checksum": "E7DCA4989847DB4237589153FF6CC572B212C8DD1640219B6788BADFC8F9A3EF",
      "algorithm": "sha256"
    },
    {
      "id": "github_release/github.com/denoland/deno/v2.5.2/deno-x86_64-apple-darwin.zip",
      "checksum": "D7E93D8EB0ACFEA43E989F0599C95A8845BA3D35F0E43DE8FA6263BE749A810E",
      "algorithm": "sha256"
    },
    {
      "id": "github_release/github.com/denoland/deno/v2.5.2/deno-x86_64-pc-windows-msvc.zip",
      "checksum": "5201C10F36BD9CFC090847BB7174296A1F3C154A539CEE99BA092C358D07FDC7",
      "algorithm": "sha256"
    },
    {
      "id": "github_release/github.com/denoland/deno/v2.5.2/deno-x86_64-unknown-linux-gnu.zip",
      "checksum": "520FD4BC2D18B50B6AC2EA8B7D0F7F6A35588E412754A081E8C6AFD4B15264C4",
      "algorithm": "sha256"
    },
    {
      "id": "github_release/github.com/direnv/direnv/v2.37.1/direnv.darwin-amd64",
      "checksum": "24FB9CE48B563D7E9FBDD3A4E3E836941654A31CE3E67EBA9EAAFC3DCD8AE73B",
      "algorithm": "sha256"
    },
    {
      "id": "github_release/github.com/direnv/direnv/v2.37.1/direnv.darwin-arm64",
      "checksum": "4F569F3A36732BFD8B8FEA7BFCC6AD87A59745C109022164D0CA4832451D5369",
      "algorithm": "sha256"
    },
    {
      "id": "github_release/github.com/direnv/direnv/v2.37.1/direnv.linux-amd64",
      "checksum": "1F1B93DD6F38523FDE26DFAC96151EF9D31A374E3005CD3345FB93555AE0C9B5",
      "algorithm": "sha256"
    },
    {
      "id": "github_release/github.com/direnv/direnv/v2.37.1/direnv.linux-arm64",
      "checksum": "2A9CEF8D73521D6A3EC3F2871C4B747B8C4CC038628C1B57A7EFA42B393A2D82",
      "algorithm": "sha256"
    },
    {
      "id": "github_release/github.com/direnv/direnv/v2.37.1/direnv.windows-amd64",
      "checksum": "D96FC8B7CF020C2D4C1DBBC2CCEC5FD1CAB05B51C491F02C8527A7FA6C50A1CD",
      "algorithm": "sha256"
    },
    {
      "id": "github_release/github.com/direnv/direnv/v2.37.1/direnv.windows-arm64",
      "checksum": "6802F722F5EF12562D6E3E15C26F39E34B337E5BE12EA22F17284552CD782298",
      "algorithm": "sha256"
    },
    {
      "id": "github_release/github.com/eza-community/eza/v0.23.3/eza.exe_x86_64-pc-windows-gnu.tar.gz",
      "checksum": "0A2DF426DD8BF7B9697C631AE96AF2D52641EE4DAA8FB07863C82E77BE5480A2",
      "algorithm": "sha256"
    },
    {
      "id": "github_release/github.com/eza-community/eza/v0.23.3/eza_aarch64-unknown-linux-gnu.tar.gz",
      "checksum": "333246365F1A3325DF1068FF8BC994EA3A3E04ABE4E118FA11015D589C5CC41D",
      "algorithm": "sha256"
    },
    {
      "id": "github_release/github.com/eza-community/eza/v0.23.3/eza_x86_64-unknown-linux-musl.tar.gz",
      "checksum": "9394077C94CED5A39B895092A4E59B21C3949B414A1AFFB08C47BE6A3AF17ECA",
      "algorithm": "sha256"
    },
    {
      "id": "github_release/github.com/github/copilot-language-server-release/1.378.0/copilot-language-server-darwin-arm64-1.378.0.zip",
      "checksum": "FBB15E2AF7B37CF1809C23E3CE8A9A4E3D3EEF6A4D4B5F4A2CB1FF3B05652A1A",
      "algorithm": "sha256"
    },
    {
      "id": "github_release/github.com/github/copilot-language-server-release/1.378.0/copilot-language-server-darwin-x64-1.378.0.zip",
      "checksum": "8855C66F95B1779F174744C0C6BE45A1C14326696D0FE250FAD3C303D45C4E4F",
      "algorithm": "sha256"
    },
    {
      "id": "github_release/github.com/github/copilot-language-server-release/1.378.0/copilot-language-server-linux-arm64-1.378.0.zip",
      "checksum": "CDFB83FCA35B71F666099926D15F6A63444BB091F9178679A4FF3659F6CC61D5",
      "algorithm": "sha256"
    },
    {
      "id": "github_release/github.com/github/copilot-language-server-release/1.378.0/copilot-language-server-linux-x64-1.378.0.zip",
      "checksum": "DCB03F64FEC6533095F238171BCE8B2965C8DFC076514B507E5C1B628D8D5CD6",
      "algorithm": "sha256"
    },
    {
      "id": "github_release/github.com/github/copilot-language-server-release/1.378.0/copilot-language-server-win32-x64-1.378.0.zip",
      "checksum": "2EA7D35F77ACCFFE7058B234BB26A33F566E26510C4429B28E5882DDDF9A3AC6",
      "algorithm": "sha256"
    },
    {
      "id": "github_release/github.com/github/github-mcp-server/v0.17.0/github-mcp-server_Darwin_arm64.tar.gz",
      "checksum": "EE4F2FF2CB4CE221289B6F9322A9860554AF030283146A86362457E66B159E45",
      "algorithm": "sha256"
    },
    {
      "id": "github_release/github.com/github/github-mcp-server/v0.17.0/github-mcp-server_Darwin_x86_64.tar.gz",
      "checksum": "7DAD8F26615BE6551A67D096E41B32A8B8FB882FECBF6969CD02117543EB1DBA",
      "algorithm": "sha256"
    },
    {
      "id": "github_release/github.com/github/github-mcp-server/v0.17.0/github-mcp-server_Linux_arm64.tar.gz",
      "checksum": "98AB29A0FB734BBE5214BF78E45FBEE128FE4E325FADD0301F9D503BD5534295",
      "algorithm": "sha256"
    },
    {
      "id": "github_release/github.com/github/github-mcp-server/v0.17.0/github-mcp-server_Linux_x86_64.tar.gz",
      "checksum": "B6BB5D43001705569D79A1AB0AA2B8B0D33AAC8624A3B68A95D00F7698788DE9",
      "algorithm": "sha256"
    },
    {
      "id": "github_release/github.com/github/github-mcp-server/v0.17.0/github-mcp-server_Windows_arm64.zip",
      "checksum": "1AE69E4395FEFFA567F5F040977CE3332386167358CEFEA25EAE5775D3674B0E",
      "algorithm": "sha256"
    },
    {
      "id": "github_release/github.com/github/github-mcp-server/v0.17.0/github-mcp-server_Windows_x86_64.zip",
      "checksum": "BC3003044A39439B4569526F9999AB81D2BCABFBD145281F2C62046A6E40902E",
      "algorithm": "sha256"
    },
    {
      "id": "github_release/github.com/golangci/golangci-lint/v1.64.8/golangci-lint-1.64.8-darwin-amd64.tar.gz",
      "checksum": "B52AEBB8CB51E00BFD5976099083FBE2C43EF556CEF9C87E58A8AE656E740444",
      "algorithm": "sha256"
    },
    {
      "id": "github_release/github.com/golangci/golangci-lint/v1.64.8/golangci-lint-1.64.8-darwin-arm64.tar.gz",
      "checksum": "70543D21E5B02A94079BE8AA11267A5B060865583E337FE768D39B5D3E2FAF1F",
      "algorithm": "sha256"
    },
    {
      "id": "github_release/github.com/golangci/golangci-lint/v1.64.8/golangci-lint-1.64.8-linux-amd64.tar.gz",
      "checksum": "B6270687AFB143D019F387C791CD2A6F1CB383BE9B3124D241CA11BD3CE2E54E",
      "algorithm": "sha256"
    },
    {
      "id": "github_release/github.com/golangci/golangci-lint/v1.64.8/golangci-lint-1.64.8-linux-arm64.tar.gz",
      "checksum": "A6AB58EBCB1C48572622146CDAEC2956F56871038A54ED1149F1386E287789A5",
      "algorithm": "sha256"
    },
    {
      "id": "github_release/github.com/golangci/golangci-lint/v1.64.8/golangci-lint-1.64.8-windows-amd64.zip",
      "checksum": "54C2ED3A6B4F2F5DA1056FB6E83D6B73B592E06684B65A5999174FABBB251A8F",
      "algorithm": "sha256"
    },
    {
      "id": "github_release/github.com/golangci/golangci-lint/v1.64.8/golangci-lint-1.64.8-windows-arm64.zip",
      "checksum": "24294BC46BC887691C7A43C66448F1DF9203C0A9C15BCB114B6147AA97973505",
      "algorithm": "sha256"
    },
    {
      "id": "github_release/github.com/grafana/jsonnet-language-server/v0.16.0/jsonnet-language-server_0.16.0_darwin_amd64",
      "checksum": "F37D57FCF851E18FECC3B3867A8E06305EE315E01A9430BF5448438EFF86736C",
      "algorithm": "sha256"
    },
    {
      "id": "github_release/github.com/grafana/jsonnet-language-server/v0.16.0/jsonnet-language-server_0.16.0_darwin_arm64",
      "checksum": "8B6E642374D3004C3AC35254874ED1D14203A85C979F6684FC6218F58A8072D4",
      "algorithm": "sha256"
    },
    {
      "id": "github_release/github.com/grafana/jsonnet-language-server/v0.16.0/jsonnet-language-server_0.16.0_linux_amd64",
      "checksum": "42C7D38515E5A2008DE26D678140E2D7FD1825EB977D78023FE997913E3DC2BE",
      "algorithm": "sha256"
    },
    {
      "id": "github_release/github.com/grafana/jsonnet-language-server/v0.16.0/jsonnet-language-server_0.16.0_linux_arm64",
      "checksum": "155933CBBDA25E9D89B6E14F1C2C52089CDFE82700FDA60D8EBAABAD2C409F18",
      "algorithm": "sha256"
    },
    {
      "id": "github_release/github.com/grafana/jsonnet-language-server/v0.16.0/jsonnet-language-server_0.16.0_windows_amd64.exe",
      "checksum": "53D233A1927AFA52F39A2AE5396DC7FFEB13283B5F13EDFA6DFDC1F41E71199B",
      "algorithm": "sha256"
    },
    {
      "id": "github_release/github.com/grafana/jsonnet-language-server/v0.16.0/jsonnet-language-server_0.16.0_windows_arm64.exe",
      "checksum": "8DAC64BB1E1F215988E3EA8FD2FBFE575251E3B07BA95E9BE3BC3EA3175E3522",
      "algorithm": "sha256"
    },
    {
      "id": "github_release/github.com/hadolint/hadolint/v2.14.0/hadolint-linux-arm64",
      "checksum": "331F1D3511B84A4F1E3D18D52FEC284723E4019552F4F47B19322A53CE9A40ED",
      "algorithm": "sha256"
    },
    {
      "id": "github_release/github.com/hadolint/hadolint/v2.14.0/hadolint-linux-x86_64",
      "checksum": "6BF226944684F56C84DD014E8B979D27425C0148F61B3BD99BCC6F39E9DC5A47",
      "algorithm": "sha256"
    },
    {
      "id": "github_release/github.com/hadolint/hadolint/v2.14.0/hadolint-macos-arm64",
      "checksum": "3625E2E9F43DCFE7BD38738A5F5520ED50CE39ED28485266E6803DD7BC197B10",
      "algorithm": "sha256"
    },
    {
      "id": "github_release/github.com/hadolint/hadolint/v2.14.0/hadolint-macos-x86_64",
      "checksum": "2B69A853433F1ECA522FFB921CD490BD1321424D03331FD8390F93B7FB4A02E9",
      "algorithm": "sha256"
    },
    {
      "id": "github_release/github.com/hadolint/hadolint/v2.14.0/hadolint-windows-x86_64.exe",
      "checksum": "8E0EE174F88EDB14F207A68430C7A53C2883ED509CDBDE9A3A26FFFA140FA5E4",
      "algorithm": "sha256"
    },
    {
      "id": "github_release/github.com/jesseduffield/lazydocker/v0.24.1/lazydocker_0.24.1_Darwin_arm64.tar.gz",
      "checksum": "55D8FF53D9BD36EE088393154442D3B93DB787118BE5AD0AE80C200D76311EC2",
      "algorithm": "sha256"
    },
    {
      "id": "github_release/github.com/jesseduffield/lazydocker/v0.24.1/lazydocker_0.24.1_Darwin_x86_64.tar.gz",
      "checksum": "7B4C73C7B1B62B9702A701AC0A8A1D8913602173362E8EE96D4FC03EF556AD10",
      "algorithm": "sha256"
    },
    {
      "id": "github_release/github.com/jesseduffield/lazydocker/v0.24.1/lazydocker_0.24.1_Linux_arm64.tar.gz",
      "checksum": "C38E715F2CB56440BEC16E3744005522C1D13C47D2E3730572849DC69CEFD8AE",
      "algorithm": "sha256"
    },
    {
      "id": "github_release/github.com/jesseduffield/lazydocker/v0.24.1/lazydocker_0.24.1_Linux_x86_64.tar.gz",
      "checksum": "461CACF618E1020DFF1D7896248C1C1F2267D5C25FB529755E4B9C43C5D1D4A5",
      "algorithm": "sha256"
    },
    {
      "id": "github_release/github.com/jesseduffield/lazydocker/v0.24.1/lazydocker_0.24.1_Windows_arm64.zip",
      "checksum": "8D965FF79409802FF620F744F91CB932BE52B25C2A5ED7AA5131387645151EB8",
      "algorithm": "sha256"
    },
    {
      "id": "github_release/github.com/jesseduffield/lazydocker/v0.24.1/lazydocker_0.24.1_Windows_x86_64.zip",
      "checksum": "CC54494D8CD9232D8D64CF4C2D720A045E5B969A716739424702577F55B53CF9",
      "algorithm": "sha256"
    },
    {
      "id": "github_release/github.com/jesseduffield/lazygit/v0.55.1/lazygit_0.55.1_darwin_arm64.tar.gz",
      "checksum": "D5761DA15DC95348E4D508CE3245A132A6129DBACE866144B24591F2A5C73B8E",
      "algorithm": "sha256"
    },
    {
      "id": "github_release/github.com/jesseduffield/lazygit/v0.55.1/lazygit_0.55.1_darwin_x86_64.tar.gz",
      "checksum": "897BA15196167C9853F2493D6F434CF7283000E9732B175035129334383232CD",
      "algorithm": "sha256"
    },
    {
      "id": "github_release/github.com/jesseduffield/lazygit/v0.55.1/lazygit_0.55.1_linux_arm64.tar.gz",
      "checksum": "EBAA6DA4221F036A8C5BAB865241EBAABC990752307F4CF59A89DCA520F3F59F",
      "algorithm": "sha256"
    },
    {
      "id": "github_release/github.com/jesseduffield/lazygit/v0.55.1/lazygit_0.55.1_linux_x86_64.tar.gz",
      "checksum": "6385A699DDE302B7FDCD1CC8910AE225ED0C19A230285569C586051576F0D6A3",
      "algorithm": "sha256"
    },
    {
      "id": "github_release/github.com/jesseduffield/lazygit/v0.55.1/lazygit_0.55.1_windows_arm64.zip",
      "checksum": "B35BDA03EDD3373AECCE0D8E0D50A36D3BD9F8E3D8665CF242A1985EE243B6D4",
      "algorithm": "sha256"
    },
    {
      "id": "github_release/github.com/jesseduffield/lazygit/v0.55.1/lazygit_0.55.1_windows_x86_64.zip",
      "checksum": "061385101E80ED99CBDA1B9243B9F1A691B63DF656E6D025B395642B76262E02",
      "algorithm": "sha256"
    },
    {
      "id": "github_release/github.com/jqlang/jq/jq-1.8.1/jq-linux-amd64",
      "checksum": "020468DE7539CE70EF1BCEAF7CDE2E8C4F2CA6C3AFB84642AABC5C97D9FC2A0D",
      "algorithm": "sha256"
    },
    {
      "id": "github_release/github.com/jqlang/jq/jq-1.8.1/jq-linux-arm64",
      "checksum": "6BC62F25981328EDD3CFCFE6FE51B073F2D7E7710D7EF7FCDAC28D4E384FC3D4",
      "algorithm": "sha256"
    },
    {
      "id": "github_release/github.com/jqlang/jq/jq-1.8.1/jq-macos-amd64",
      "checksum": "E80DBE0D2A2597E3C11C404F03337B981D74B4A8504B70586C354B7697A7C27F",
      "algorithm": "sha256"
    },
    {
      "id": "github_release/github.com/jqlang/jq/jq-1.8.1/jq-macos-arm64",
      "checksum": "A9FE3EA2F86DFC72F6728417521EC9067B343277152B114F4E98D8CB0E263603",
      "algorithm": "sha256"
    },
    {
      "id": "github_release/github.com/jqlang/jq/jq-1.8.1/jq-windows-amd64.exe",
      "checksum": "23CB60A1354EED6BCC8D9B9735E8C7B388CD1FDCB75726B93BC299EF22DD9334",
      "algorithm": "sha256"
    },
    {
      "id": "github_release/github.com/junegunn/fzf/v0.65.2/fzf-0.65.2-darwin_amd64.tar.gz",
      "checksum": "4F2D7414E4DBE2469E5581C5830F29B1ED3532A3D672646E6C2E0533FC07CBEA",
      "algorithm": "sha256"
    },
    {
      "id": "github_release/github.com/junegunn/fzf/v0.65.2/fzf-0.65.2-darwin_arm64.tar.gz",
      "checksum": "A1464F1D4B75C3A92975F67055F9E407800ED35820EA7D73F2AFB90AEB0491E8",
      "algorithm": "sha256"
    },
    {
      "id": "github_release/github.com/junegunn/fzf/v0.65.2/fzf-0.65.2-linux_amd64.tar.gz",
      "checksum": "5EB8EFC0E94AA559F84EA83EEBA99BEA7DCE818E63F92B4B62E60663220F1C14",
      "algorithm": "sha256"
    },
    {
      "id": "github_release/github.com/junegunn/fzf/v0.65.2/fzf-0.65.2-linux_arm64.tar.gz",
      "checksum": "097347160595BF03A426D2ABE0A17E14CA060540DDFC0EA45C0A9BE62BB29A2B",
      "algorithm": "sha256"
    },
    {
      "id": "github_release/github.com/junegunn/fzf/v0.65.2/fzf-0.65.2-windows_amd64.zip",
      "checksum": "AD77A1E4B6EA6B790B02BFAD333EB3E2A802E5E5423271733B324794EDA31B9E",
      "algorithm": "sha256"
    },
    {
      "id": "github_release/github.com/junegunn/fzf/v0.65.2/fzf-0.65.2-windows_arm64.zip",
      "checksum": "FA15B9DA97C1BABCAB7D6E2992045F9237AAA06A13498CD78FA0367558F003A3",
      "algorithm": "sha256"
    },
    {
      "id": "github_release/github.com/mvdan/sh/v3.12.0/shfmt_v3.12.0_darwin_amd64",
      "checksum": "C31548693DE6584E6164B7ED5FBB7B4A083F2D937CA94B4E0DDF59AA461A85E4",
      "algorithm": "sha256"
    },
    {
      "id": "github_release/github.com/mvdan/sh/v3.12.0/shfmt_v3.12.0_darwin_arm64",
      "checksum": "D903802E0CE3ECBC82B98512F55BA370B0D37A93F3F78DE394F5B657052B33DD",
      "algorithm": "sha256"
    },
    {
      "id": "github_release/github.com/mvdan/sh/v3.12.0/shfmt_v3.12.0_linux_amd64",
      "checksum": "D9FBB2A9C33D13F47E7618CF362A914D029D02A6DF124064FFF04FD688A745EA",
      "algorithm": "sha256"
    },
    {
      "id": "github_release/github.com/mvdan/sh/v3.12.0/shfmt_v3.12.0_linux_arm64",
      "checksum": "5F3FE3FA6A9F766E6A182BA79A94BEF8AFEDAFC57DB0B1AD32B0F67FAE971BA4",
      "algorithm": "sha256"
    },
    {
      "id": "github_release/github.com/mvdan/sh/v3.12.0/shfmt_v3.12.0_windows_amd64.exe",
      "checksum": "C8BDA517BA1C640CE4A715C0FA665439DDBE4357BA5E9B77B0E51E70E2B9C94B",
      "algorithm": "sha256"
    },
    {
      "id": "github_release/github.com/nametake/golangci-lint-langserver/v0.0.11/golangci-lint-langserver_Darwin_arm64.tar.gz",
      "checksum": "D9F704E6AE3BA63B8F452DFEC3C9B2B418652AD3BA3A1D0B92AE70FD2C74D2B1",
      "algorithm": "sha256"
    },
    {
      "id": "github_release/github.com/nametake/golangci-lint-langserver/v0.0.11/golangci-lint-langserver_Darwin_x86_64.tar.gz",
      "checksum": "FA6629E251FD7F82E330FF85D3E63AF3D1986374AD538A6A26D4A855B3E3009F",
      "algorithm": "sha256"
    },
    {
      "id": "github_release/github.com/nametake/golangci-lint-langserver/v0.0.11/golangci-lint-langserver_Linux_arm64.tar.gz",
      "checksum": "7D3695A366E653569A375D209516B3FA8CA184B92FC5ACBFEDFAEE9AD3C97C21",
      "algorithm": "sha256"
    },
    {
      "id": "github_release/github.com/nametake/golangci-lint-langserver/v0.0.11/golangci-lint-langserver_Linux_x86_64.tar.gz",
      "checksum": "B4EFA95267C29CA4D08E0A977E90E7C6A8A606BAFE1DCEDFD5E48E952536B331",
      "algorithm": "sha256"
    },
    {
      "id": "github_release/github.com/nametake/golangci-lint-langserver/v0.0.11/golangci-lint-langserver_Windows_arm64.zip",
      "checksum": "4DEEF94143C5C45D9513B7D1507B118FC989D360612FB440811CFFD39028E872",
      "algorithm": "sha256"
    },
    {
      "id": "github_release/github.com/nametake/golangci-lint-langserver/v0.0.11/golangci-lint-langserver_Windows_x86_64.zip",
      "checksum": "6A4620EE48D94406BA1E0E986D4F9F1D926BBAB2212B3F5D9D106F80A67A3037",
      "algorithm": "sha256"
    },
    {
      "id": "github_release/github.com/neovim/neovim/v0.11.4/nvim-linux-arm64.tar.gz",
      "checksum": "684E4262D2296E469CB43F0D05EDBBB52B960B7F117BED6B22936FC768993CD9",
      "algorithm": "sha256"
    },
    {
      "id": "github_release/github.com/neovim/neovim/v0.11.4/nvim-linux-x86_64.tar.gz",
      "checksum": "A74740047E73B2B380D63A474282814063D10650CD6CC95EFA16D1713C7E616C",
      "algorithm": "sha256"
    },
    {
      "id": "github_release/github.com/neovim/neovim/v0.11.4/nvim-macos-arm64.tar.gz",
      "checksum": "2DE9623A4AA8CEDF85C51E33BF8E85E05F6F291B923CD666C04704CCF164E8B7",
      "algorithm": "sha256"
    },
    {
      "id": "github_release/github.com/neovim/neovim/v0.11.4/nvim-macos-x86_64.tar.gz",
      "checksum": "567B89138C29386F67A00FC8E26C6469C8BF0E5707DFEA5E3FBAF4E21294D9EB",
      "algorithm": "sha256"
    },
    {
      "id": "github_release/github.com/neovim/neovim/v0.11.4/nvim-win64.zip",
      "checksum": "77EEE5936724B82E45B448E0370ABE0911D75FAD551C0A25415F4E51719FAF34",
      "algorithm": "sha256"
    },
    {
      "id": "github_release/github.com/pnpm/pnpm/v10.17.1/pnpm-linux-arm64",
      "checksum": "64601480FC29B88A615007E3D439B19330B1A897D59E159F08A0CE369923DF3F",
      "algorithm": "sha256"
    },
    {
      "id": "github_release/github.com/pnpm/pnpm/v10.17.1/pnpm-linux-x64",
      "checksum": "5BF591D8A3D5E14DBB15524B65A139A81F4B5954BC214BA0C014968899086C3A",
      "algorithm": "sha256"
    },
    {
      "id": "github_release/github.com/pnpm/pnpm/v10.17.1/pnpm-macos-arm64",
      "checksum": "AAA3B6DC7C7C13364CA2E7088FE1E1FA5D02EA8756997B57868CD0C46F558224",
      "algorithm": "sha256"
    },
    {
      "id": "github_release/github.com/pnpm/pnpm/v10.17.1/pnpm-macos-x64",
      "checksum": "2465A24A786FDAAD5C80B1806E3ED84779BEA9FD83F90A25F8DBC7F40741CDAC",
      "algorithm": "sha256"
    },
    {
      "id": "github_release/github.com/pnpm/pnpm/v10.17.1/pnpm-win-x64.exe",
      "checksum": "C050AB19B9FD5888D5BCAF8A3D7308FDBCB0C5D7C8065C98B4091E9DC1F3B0F0",
      "algorithm": "sha256"
    },
    {
      "id": "github_release/github.com/rhysd/actionlint/v1.7.7/actionlint_1.7.7_darwin_amd64.tar.gz",
      "checksum": "28E5DE5A05FC558474F638323D736D822FFF183D2D492F0AECB2B73CC44584F5",
      "algorithm": "sha256"
    },
    {
      "id": "github_release/github.com/rhysd/actionlint/v1.7.7/actionlint_1.7.7_darwin_arm64.tar.gz",
      "checksum": "2693315B9093AEACB4EBD91A993FEA54FC215057BF0DA2659056B4BC033873DB",
      "algorithm": "sha256"
    },
    {
      "id": "github_release/github.com/rhysd/actionlint/v1.7.7/actionlint_1.7.7_linux_amd64.tar.gz",
      "checksum": "023070A287CD8CCCD71515FEDC843F1985BF96C436B7EFFAECCE67290E7E0757",
      "algorithm": "sha256"
    },
    {
      "id": "github_release/github.com/rhysd/actionlint/v1.7.7/actionlint_1.7.7_linux_arm64.tar.gz",
      "checksum": "401942F9C24ED71E4FE71B76C7D638F66D8633575C4016EFD2977CE7C28317D0",
      "algorithm": "sha256"
    },
    {
      "id": "github_release/github.com/rhysd/actionlint/v1.7.7/actionlint_1.7.7_windows_amd64.zip",
      "checksum": "7F12F1801BCA3D480D67AAF7774F4C2A6359A3CA8EEBE382C95C10C9704AA731",
      "algorithm": "sha256"
    },
    {
      "id": "github_release/github.com/rhysd/actionlint/v1.7.7/actionlint_1.7.7_windows_arm64.zip",
      "checksum": "76E9514CFAC18E5677AA04F3A89873C981F16A2F2353BB97372A86CD09B1F5A8",
      "algorithm": "sha256"
    },
    {
      "id": "github_release/github.com/rossmacarthur/sheldon/0.8.5/sheldon-0.8.5-aarch64-apple-darwin.tar.gz",
      "checksum": "6E47F10A25F165B095EB2BDE1AB617D4D34AD6F3FF2CA984167CA94FADD52730",
      "algorithm": "sha256"
    },
    {
      "id": "github_release/github.com/rossmacarthur/sheldon/0.8.5/sheldon-0.8.5-aarch64-unknown-linux-musl.tar.gz",
      "checksum": "1F6B792E49E259F7C313E9921C8D4AD638D827ABC2C023EFE0588A55678F9A3E",
      "algorithm": "sha256"
    },
    {
      "id": "github_release/github.com/rossmacarthur/sheldon/0.8.5/sheldon-0.8.5-x86_64-unknown-linux-musl.tar.gz",
      "checksum": "80AA0BE617072C278D67FD6C5FBCE4903D3801D78B6ABF8F058F0648D2242C78",
      "algorithm": "sha256"
    },
    {
      "id": "github_release/github.com/sharkdp/bat/v0.25.0/bat-v0.25.0-aarch64-apple-darwin.tar.gz",
      "checksum": "B3ED5A7515545445881F1036F0CC1B708C2B86CBCE01C1B4033F38E0CFCC7B3C",
      "algorithm": "sha256"
    },
    {
      "id": "github_release/github.com/sharkdp/bat/v0.25.0/bat-v0.25.0-aarch64-unknown-linux-musl.tar.gz",
      "checksum": "EE0F12CF6006A79CF4CCF75D2DDCF9F6BA124644503244B1AF909C2F72A2A9F7",
      "algorithm": "sha256"
    },
    {
      "id": "github_release/github.com/sharkdp/bat/v0.25.0/bat-v0.25.0-x86_64-apple-darwin.tar.gz",
      "checksum": "B974AA834B6B65610090AED2BC7310D11C6F500105696D23A130AEE24FD8380F",
      "algorithm": "sha256"
    },
    {
      "id": "github_release/github.com/sharkdp/bat/v0.25.0/bat-v0.25.0-x86_64-pc-windows-msvc.zip",
      "checksum": "1D5CED071BA9C765E16F4065877C178CEFCFD2FE9581E9DDC92AF265B73991BD",
      "algorithm": "sha256"
    },
    {
      "id": "github_release/github.com/sharkdp/bat/v0.25.0/bat-v0.25.0-x86_64-unknown-linux-musl.tar.gz",
      "checksum": "93F47D76ABE328C402EF712E9AC92AA6D5BC84D5ADCBCAF0BBC5665E5275A941",
      "algorithm": "sha256"
    },
    {
      "id": "github_release/github.com/sharkdp/fd/v10.3.0/fd-v10.3.0-aarch64-apple-darwin.tar.gz",
      "checksum": "0570263812089120BC2A5D84F9E65CD0C25E4A4D724C80075C357239C74AE904",
      "algorithm": "sha256"
    },
    {
      "id": "github_release/github.com/sharkdp/fd/v10.3.0/fd-v10.3.0-aarch64-unknown-linux-musl.tar.gz",
      "checksum": "996B9B1366433B211CB3BBEDBA91C9DBCE2431842144D925428EAD0ADF32020B",
      "algorithm": "sha256"
    },
    {
      "id": "github_release/github.com/sharkdp/fd/v10.3.0/fd-v10.3.0-x86_64-apple-darwin.tar.gz",
      "checksum": "50D30F13FE3D5914B14C4FFF5ABCBD4D0CDAB4B855970A6956F4F006C17117A3",
      "algorithm": "sha256"
    },
    {
      "id": "github_release/github.com/sharkdp/fd/v10.3.0/fd-v10.3.0-x86_64-pc-windows-msvc.zip",
      "checksum": "318AA2A6FA664325933E81FDA60D523FFF29444129E91EBF0726B5B3BCD8B059",
      "algorithm": "sha256"
    },
    {
      "id": "github_release/github.com/sharkdp/fd/v10.3.0/fd-v10.3.0-x86_64-unknown-linux-musl.tar.gz",
      "checksum": "2B6BFAAE8C48F12050813C2FFE1884C61EA26E750D803DF9C9114550A314CD14",
      "algorithm": "sha256"
    },
    {
      "id": "github_release/github.com/starship/starship/v1.23.0/starship-aarch64-apple-darwin.tar.gz",
      "checksum": "042C8001275316836A3C43FDB88D0787395EDFD0C10D209E4892AB5577B80D57",
      "algorithm": "sha256"
    },
    {
      "id": "github_release/github.com/starship/starship/v1.23.0/starship-aarch64-pc-windows-msvc.zip",
      "checksum": "B89470C308FA2FA4BF77D0DF8EA9C74D8102817BE936B2367959845C60008BAA",
      "algorithm": "sha256"
    },
    {
      "id": "github_release/github.com/starship/starship/v1.23.0/starship-aarch64-unknown-linux-musl.tar.gz",
      "checksum": "D37040138C68B5F3334BBE16D4615F0A83829DEEBECC5D014E779C302E8270D8",
      "algorithm": "sha256"
    },
    {
      "id": "github_release/github.com/starship/starship/v1.23.0/starship-x86_64-apple-darwin.tar.gz",
      "checksum": "8CAC7A18FB1FAF0AEC50BD221DD71ECC8553850D99C212231851AE64BA11F089",
      "algorithm": "sha256"
    },
    {
      "id": "github_release/github.com/starship/starship/v1.23.0/starship-x86_64-pc-windows-msvc.zip",
      "checksum": "50E670DDA19BCC480AE4D1F7F0D3C7A092693252292406B54ABABA706100F03C",
      "algorithm": "sha256"
    },
    {
      "id": "github_release/github.com/starship/starship/v1.23.0/starship-x86_64-unknown-linux-musl.tar.gz",
      "checksum": "8D06D2CC67AEDD6316FF58AB679FB80CDED0D85DE1DCD5727DF0633D35356D57",
      "algorithm": "sha256"
    },
    {
      "id": "github_release/github.com/stripe/stripe-cli/v1.31.0/stripe_1.31.0_linux_arm64.tar.gz",
      "checksum": "7EC9C8C3CFEA6FA2D5CC0E181BD3CBA9C64553D86B2B3C544E6F602823E46187",
      "algorithm": "sha256"
    },
    {
      "id": "github_release/github.com/stripe/stripe-cli/v1.31.0/stripe_1.31.0_linux_x86_64.tar.gz",
      "checksum": "6E189FD25AFF733874B492127A1C514FAD1B59E2CFE96800E6CC85DC16D1DDE2",
      "algorithm": "sha256"
    },
    {
      "id": "github_release/github.com/stripe/stripe-cli/v1.31.0/stripe_1.31.0_mac-os_arm64.tar.gz",
      "checksum": "B4D2B0635A889D40973CCEA07BC148709FA51B8BAAD27D88DACDC9C88431A9C3",
      "algorithm": "sha256"
    },
    {
      "id": "github_release/github.com/stripe/stripe-cli/v1.31.0/stripe_1.31.0_mac-os_x86_64.tar.gz",
      "checksum": "F8053DD94434EE6C3962F71609264C1B6382C0F31D0DAB9AB7943FAB2D3E14D7",
      "algorithm": "sha256"
    },
    {
      "id": "github_release/github.com/stripe/stripe-cli/v1.31.0/stripe_1.31.0_windows_x86_64.zip",
      "checksum": "54FACC7D1F0BCB64A972EE6B06CCC284985E2BA78DA068DF915DD4346C62892F",
      "algorithm": "sha256"
    },
    {
      "id": "github_release/github.com/sxyazi/yazi/v25.5.31/yazi-aarch64-apple-darwin.zip",
      "checksum": "8BDF137E8F84CD11F9DD866FF2B68E4886D1055AB21FE2E0C6F6A0515D2BFD70",
      "algorithm": "sha256"
    },
    {
      "id": "github_release/github.com/sxyazi/yazi/v25.5.31/yazi-aarch64-unknown-linux-musl.zip",
      "checksum": "9A838FF2D028C70D4EB4C502A75FC963AD92D2E1353133F20D9F6D5CAFB9C4D6",
      "algorithm": "sha256"
    },
    {
      "id": "github_release/github.com/sxyazi/yazi/v25.5.31/yazi-x86_64-apple-darwin.zip",
      "checksum": "2AAF4D7427914877596476242CBF1A5BDF7796A6002A0D3034A5506CA54F813B",
      "algorithm": "sha256"
    },
    {
      "id": "github_release/github.com/sxyazi/yazi/v25.5.31/yazi-x86_64-pc-windows-msvc.zip",
      "checksum": "79524A2B48BB7021078E0314D3C75AAF5AE9D69DEE2947CD7A705CBAA95D3BB9",
      "algorithm": "sha256"
    },
    {
      "id": "github_release/github.com/sxyazi/yazi/v25.5.31/yazi-x86_64-unknown-linux-musl.zip",
      "checksum": "A2FDC9C35719FA72D94820893EB2FEDD93FD1C418C2CF568702643526C358F7A",
      "algorithm": "sha256"
    },
    {
      "id": "github_release/github.com/x-motemen/ghq/v1.8.0/ghq_darwin_amd64.zip",
      "checksum": "742A64C85B7C01A1399AE286E886CFFC4649EE38891FB01CD32F31394610EA80",
      "algorithm": "sha256"
    },
    {
      "id": "github_release/github.com/x-motemen/ghq/v1.8.0/ghq_darwin_arm64.zip",
      "checksum": "0399A4DCDDEEB9E76F7F9EEB8015F91A6F093B04C14D3EB87EB563E5D94F9B0A",
      "algorithm": "sha256"
    },
    {
      "id": "github_release/github.com/x-motemen/ghq/v1.8.0/ghq_linux_amd64.zip",
      "checksum": "AD0EC7B2F52312DCA85F35B5C9E88A77447C2C71BABBD9DFEB569AB369B8E55F",
      "algorithm": "sha256"
    },
    {
      "id": "github_release/github.com/x-motemen/ghq/v1.8.0/ghq_linux_arm64.zip",
      "checksum": "982A8D0F832664B6D54A0C4089198414B97DCB33E5AED7897C5C0F0FC10E6806",
      "algorithm": "sha256"
    },
    {
      "id": "github_release/github.com/x-motemen/ghq/v1.8.0/ghq_windows_amd64.zip",
      "checksum": "F609538DD0A46987EEE933FFF8A1607DFB788DF7C396F2282821AE52BD3210BD",
      "algorithm": "sha256"
    },
    {
      "id": "github_release/github.com/x-motemen/ghq/v1.8.0/ghq_windows_arm64.zip",
      "checksum": "03E329E679B10A1B1A2C28A9BCB6D90AE9A39E273C0E8923071ABF8F72DB1C85",
      "algorithm": "sha256"
    },
    {
      "id": "http/awscli.amazonaws.com/AWSCLIV2-2.31.7.pkg",
      "checksum": "62E25C3F097C9D46E6C64E874DDED1417F82A00BBFF1708E9B27B034EBBF03B1",
      "algorithm": "sha256"
    },
    {
      "id": "http/awscli.amazonaws.com/awscli-exe-linux-aarch64-2.31.7.zip",
      "checksum": "5AF7670D38BE5D71814B7C1B4A434578D309FD3DD6986542E83D5ABC013A3E8F",
      "algorithm": "sha256"
    },
    {
      "id": "http/awscli.amazonaws.com/awscli-exe-linux-x86_64-2.31.7.zip",
      "checksum": "284BCED89E3158FE8DBF676E6B6ECF6D35B6551C37578F4008A9165D6E040990",
      "algorithm": "sha256"
    },
    {
      "id": "http/golang.org/dl/go1.25.1.darwin-amd64.tar.gz",
      "checksum": "1D622468F767A1B9FE1E1E67BD6CE6744D04E0C68712ADC689748BBECCB126BB",
      "algorithm": "sha256"
    },
    {
      "id": "http/golang.org/dl/go1.25.1.darwin-arm64.tar.gz",
      "checksum": "68DEEBB214F39D542E518EBB0598A406AB1B5A22BBA8EC9ADE9F55FB4DD94A6C",
      "algorithm": "sha256"
    },
    {
      "id": "http/golang.org/dl/go1.25.1.linux-amd64.tar.gz",
      "checksum": "7716A0D940A0F6AE8E1F3B3F4F36299DC53E31B16840DBD171254312C41CA12E",
      "algorithm": "sha256"
    },
    {
      "id": "http/golang.org/dl/go1.25.1.linux-arm64.tar.gz",
      "checksum": "65A3E34FB2126F55B34E1EDFC709121660E1BE2DEE6BDF405FC399A63A95A87D",
      "algorithm": "sha256"
    },
    {
      "id": "http/golang.org/dl/go1.25.1.windows-amd64.zip",
      "checksum": "4A974DE310E7EE1D523D2FCEDB114BA5FA75408C98EB3652023E55CCF3FA7CAB",
      "algorithm": "sha256"
    },
    {
      "id": "http/golang.org/dl/go1.25.1.windows-arm64.zip",
      "checksum": "04BC3C078E9E904C4D58D6AC2532A5BDD402BD36A9FF0B5949B3C5E6006A05EE",
      "algorithm": "sha256"
    },
    {
      "id": "registries/github_content/github.com/aquaproj/aqua-registry/v4.416.0/registry.yaml",
      "checksum": "C5E20436AF2CFF46B287E1C1ED47C9202E818BF962AA05984808EFE38CDCBB921B4FF22D2DA5CE084E9145377888136F82DC03645609B38DC6BB5A2A623B3F45",
      "algorithm": "sha512"
    }
  ]
}
