{
  "checksums": [
    {
      "id": "github_content/github.com/awslabs/git-secrets/1.3.0/git-secrets",
      "checksum": "DF9A5D2BEEDA1C83E23105F46EFE464BB4C97F8328E1E66754D7DAACFAF7272B",
      "algorithm": "sha256"
    },
    {
      "id": "github_release/github.com/BurntSushi/ripgrep/14.1.1/ripgrep-14.1.1-aarch64-apple-darwin.tar.gz",
      "checksum": "24AD76777745FBFF131C8FBC466742B011F925BFA4FFFA2DED6DEF23B5B937BE",
      "algorithm": "sha256"
    },
    {
      "id": "github_release/github.com/BurntSushi/ripgrep/14.1.1/ripgrep-14.1.1-aarch64-unknown-linux-gnu.tar.gz",
      "checksum": "C827481C4FF4EA10C9DC7A4022C8DE5DB34A5737CB74484D62EB94A95841AB2F",
      "algorithm": "sha256"
    },
    {
      "id": "github_release/github.com/BurntSushi/ripgrep/14.1.1/ripgrep-14.1.1-x86_64-apple-darwin.tar.gz",
      "checksum": "FC87E78F7CB3FEA12D69072E7EF3B21509754717B746368FD40D88963630E2B3",
      "algorithm": "sha256"
    },
    {
      "id": "github_release/github.com/BurntSushi/ripgrep/14.1.1/ripgrep-14.1.1-x86_64-pc-windows-msvc.zip",
      "checksum": "D0F534024C42AFD6CB4D38907C25CD2B249B79BBE6CC1DBEE8E3E37C2B6E25A1",
      "algorithm": "sha256"
    },
    {
      "id": "github_release/github.com/BurntSushi/ripgrep/14.1.1/ripgrep-14.1.1-x86_64-unknown-linux-musl.tar.gz",
      "checksum": "4CF9F2741E6C465FFDB7C26F38056A59E2A2544B51F7CC128EF28337EEAE4D8E",
      "algorithm": "sha256"
    },
    {
      "id": "github_release/github.com/JohnnyMorganz/StyLua/v2.2.0/stylua-linux-aarch64.zip",
      "checksum": "E3B6078AD47071E40056A976BE78C9B3BCF661759EEEB96EA2E47EDAF3060293",
      "algorithm": "sha256"
    },
    {
      "id": "github_release/github.com/JohnnyMorganz/StyLua/v2.2.0/stylua-linux-x86_64-musl.zip",
      "checksum": "D07BA799023E2790AD4DBE3E51C17491F2087F0E47C0294CFE69AC3273F29E39",
      "algorithm": "sha256"
    },
    {
      "id": "github_release/github.com/JohnnyMorganz/StyLua/v2.2.0/stylua-macos-aarch64.zip",
      "checksum": "ADDBAED63CEF8FD95AAE474885D4929B1EF42DBE3376CBE57235AA46EA62ECF7",
      "algorithm": "sha256"
    },
    {
      "id": "github_release/github.com/JohnnyMorganz/StyLua/v2.2.0/stylua-macos-x86_64.zip",
      "checksum": "B631414953F9701434E9FCC7CE0E999CED604BDDA8A644C14A043C41B07AB769",
      "algorithm": "sha256"
    },
    {
      "id": "github_release/github.com/JohnnyMorganz/StyLua/v2.2.0/stylua-windows-x86_64.zip",
      "checksum": "C88FDBA114242601D7C9A3ED9F0A7DDFB5CA0B4C85146405DAA38D459D0DFA29",
      "algorithm": "sha256"
    },
    {
      "id": "github_release/github.com/LuaLS/lua-language-server/3.15.0/lua-language-server-3.15.0-darwin-arm64.tar.gz",
      "checksum": "050F5F493F65112AFC116E31281A9F73918546782D3696485DC052724838F58B",
      "algorithm": "sha256"
    },
    {
      "id": "github_release/github.com/LuaLS/lua-language-server/3.15.0/lua-language-server-3.15.0-darwin-x64.tar.gz",
      "checksum": "01D28A31E264434E51662814A68F584AF068393CAECFA158C4DF5F7FDC3CA2F7",
      "algorithm": "sha256"
    },
    {
      "id": "github_release/github.com/LuaLS/lua-language-server/3.15.0/lua-language-server-3.15.0-linux-arm64.tar.gz",
      "checksum": "7DFF8EDFED4F34CF6325FF384791287D95F9A8DD9615A5279C7C6AF81CF8C45D",
      "algorithm": "sha256"
    },
    {
      "id": "github_release/github.com/LuaLS/lua-language-server/3.15.0/lua-language-server-3.15.0-linux-x64.tar.gz",
      "checksum": "4877B874C52FB7587707898DA9026CC3A6C854D9BBAB115EF49AC4E6A1B88007",
      "algorithm": "sha256"
    },
    {
      "id": "github_release/github.com/LuaLS/lua-language-server/3.15.0/lua-language-server-3.15.0-win32-x64.zip",
      "checksum": "76A10C05E8C947A448F00A61ACEAD4240484CD1E2E8C66D54401C67D99B77535",
      "algorithm": "sha256"
    },
    {
      "id": "github_release/github.com/Schniz/fnm/v1.38.1/fnm-arm64.zip",
      "checksum": "69FEDA9455931C26C84BE9F95F5E6F69E8B64686E68069FAB7CFC34756CD2944",
      "algorithm": "sha256"
    },
    {
      "id": "github_release/github.com/Schniz/fnm/v1.38.1/fnm-linux.zip",
      "checksum": "B69E5C9A05C1E17E4A7DE9A17DF14BA430D049F2591AF791A6F850A170296069",
      "algorithm": "sha256"
    },
    {
      "id": "github_release/github.com/Schniz/fnm/v1.38.1/fnm-macos.zip",
      "checksum": "80DEB3DB3DB45598F25AEA594C10936A7658F70826104FE37E33B4072A5E11F9",
      "algorithm": "sha256"
    },
    {
      "id": "github_release/github.com/Schniz/fnm/v1.38.1/fnm-windows.zip",
      "checksum": "377796E8F2F51EB8B5DE8983974CAA8922B83C167197B68B33962775703AD4A0",
      "algorithm": "sha256"
    },
    {
      "id": "github_release/github.com/Wilfred/difftastic/0.64.0/difft-aarch64-apple-darwin.tar.gz",
      "checksum": "E1E59FF3CF6C0837C94DDD4910D43351EC14F8C169ABCFA51E63136D14C9E528",
      "algorithm": "sha256"
    },
    {
      "id": "github_release/github.com/Wilfred/difftastic/0.64.0/difft-aarch64-unknown-linux-gnu.tar.gz",
      "checksum": "F657B0CC1BABA3B5BCDE4FDFBAFBC58F2131476ED53D01E4880898D34A1CB124",
      "algorithm": "sha256"
    },
    {
      "id": "github_release/github.com/Wilfred/difftastic/0.64.0/difft-x86_64-apple-darwin.tar.gz",
      "checksum": "D6B7F1C4A66495400F1F6E224EFDAF82AA66E8930FCB257BC9357D69D52DD69D",
      "algorithm": "sha256"
    },
    {
      "id": "github_release/github.com/Wilfred/difftastic/0.64.0/difft-x86_64-pc-windows-msvc.zip",
      "checksum": "1AC0113ADF9ADE9417EE133BED38EFE3085B7CCBB32AB620BDC36C4A9B365276",
      "algorithm": "sha256"
    },
    {
      "id": "github_release/github.com/Wilfred/difftastic/0.64.0/difft-x86_64-unknown-linux-musl.tar.gz",
      "checksum": "06DD06DA5593EE29ED9753026310C6C45E0048CD37BB5807E7F07B8F90CFEA5E",
      "algorithm": "sha256"
    },
    {
      "id": "github_release/github.com/ajeetdsouza/zoxide/v0.9.8/zoxide-0.9.8-aarch64-apple-darwin.tar.gz",
      "checksum": "3D1EC4AF7F3D351629F500B432E6C735CAF3216AB3EAA76DBE8FFBC8F3006F5A",
      "algorithm": "sha256"
    },
    {
      "id": "github_release/github.com/ajeetdsouza/zoxide/v0.9.8/zoxide-0.9.8-aarch64-pc-windows-msvc.zip",
      "checksum": "F1FB82EB558A50C43F635ABFE438BC7EE1620A9970959739CB5E9FDDF675821C",
      "algorithm": "sha256"
    },
    {
      "id": "github_release/github.com/ajeetdsouza/zoxide/v0.9.8/zoxide-0.9.8-aarch64-unknown-linux-musl.tar.gz",
      "checksum": "078CC9CC8CEDB6C45EDB84C0F5BAD53518C610859C73BDB3009A52B89652C103",
      "algorithm": "sha256"
    },
    {
      "id": "github_release/github.com/ajeetdsouza/zoxide/v0.9.8/zoxide-0.9.8-x86_64-apple-darwin.tar.gz",
      "checksum": "CFA865FFD1BA87DF2962F40EBD80C366F1D2B484F0C05B6DA6B0104F50822F86",
      "algorithm": "sha256"
    },
    {
      "id": "github_release/github.com/ajeetdsouza/zoxide/v0.9.8/zoxide-0.9.8-x86_64-pc-windows-msvc.zip",
      "checksum": "15DBD23AE3D98E2A745D0E8E3F0292402F0A2269B47519B81A6E994BACA5DB2B",
      "algorithm": "sha256"
    },
    {
      "id": "github_release/github.com/ajeetdsouza/zoxide/v0.9.8/zoxide-0.9.8-x86_64-unknown-linux-musl.tar.gz",
      "checksum": "4092EE38AA1EFDE42E4EFB2F9C872DF5388198AACAE7F1A74E5EB5C3CC7F531C",
      "algorithm": "sha256"
    },
    {
      "id": "github_release/github.com/astral-sh/uv/0.8.17/uv-aarch64-apple-darwin.tar.gz",
      "checksum": "E4D4859D7726298DAA4C12E114F269FF282B2CFC2B415DC0B2CA44AE2DBD358E",
      "algorithm": "sha256"
    },
    {
      "id": "github_release/github.com/astral-sh/uv/0.8.17/uv-aarch64-unknown-linux-musl.tar.gz",
      "checksum": "BD141B7E263935D14F5725F2A5C1C942FD89642E37683CB904F1984CE7E365F4",
      "algorithm": "sha256"
    },
    {
      "id": "github_release/github.com/astral-sh/uv/0.8.17/uv-x86_64-apple-darwin.tar.gz",
      "checksum": "31ED353CFD8E6C962E7C60617BD8A9D6B97B704C1ECB5B5ECEAFF8C6121B54AC",
      "algorithm": "sha256"
    },
    {
      "id": "github_release/github.com/astral-sh/uv/0.8.17/uv-x86_64-pc-windows-msvc.zip",
      "checksum": "0D051779FBCB173B183EFEAE1C3E96148764FD82709BBBF0966DF3EFE48B67C5",
      "algorithm": "sha256"
    },
    {
      "id": "github_release/github.com/astral-sh/uv/0.8.17/uv-x86_64-unknown-linux-musl.tar.gz",
      "checksum": "4057052999A210FE78D93599D2165DA9E24C8BBB23370CDD26B66A98AB479203",
      "algorithm": "sha256"
    },
    {
      "id": "github_release/github.com/auth0/auth0-cli/v1.20.0/auth0-cli_1.20.0_Darwin_arm64.tar.gz",
      "checksum": "88F71F8787596ECE91AF454B5A0ED974BA9C4F26AE76181B10D4EBAC6D0A1CB9",
      "algorithm": "sha256"
    },
    {
      "id": "github_release/github.com/auth0/auth0-cli/v1.20.0/auth0-cli_1.20.0_Darwin_x86_64.tar.gz",
      "checksum": "1721B2614A23D2DC943B4FF8415B50411C07E9E8BE9201C82C17C0A694C7182F",
      "algorithm": "sha256"
    },
    {
      "id": "github_release/github.com/auth0/auth0-cli/v1.20.0/auth0-cli_1.20.0_Linux_arm64.tar.gz",
      "checksum": "5F99F9958B0D839B2D99D28F971EE968CFB7737914C3A99BA99E347834012B86",
      "algorithm": "sha256"
    },
    {
      "id": "github_release/github.com/auth0/auth0-cli/v1.20.0/auth0-cli_1.20.0_Linux_x86_64.tar.gz",
      "checksum": "0B0A952F6D34633D64E268C31B424543C716F51E1B807C95FB09756245A880AD",
      "algorithm": "sha256"
    },
    {
      "id": "github_release/github.com/auth0/auth0-cli/v1.20.0/auth0-cli_1.20.0_Windows_arm64.zip",
      "checksum": "0D2DBC80780834A9E913458A1D69162C32C9967D47461126CB3619D045BF85C4",
      "algorithm": "sha256"
    },
    {
      "id": "github_release/github.com/auth0/auth0-cli/v1.20.0/auth0-cli_1.20.0_Windows_x86_64.zip",
      "checksum": "9C4F1DC6AB6455E5B2BD3C23E718054BF431C7C1347C64D2C70E97AB490592B9",
      "algorithm": "sha256"
    },
    {
      "id": "github_release/github.com/bufbuild/buf/v1.57.0/buf-Darwin-arm64.tar.gz",
      "checksum": "F532DB00D61669D46D382176B64526617D95EEA0131831727ED5E36EC43DCF8E",
      "algorithm": "sha256"
    },
    {
      "id": "github_release/github.com/bufbuild/buf/v1.57.0/buf-Darwin-x86_64.tar.gz",
      "checksum": "DF0E277884BE33D56D12BDA8B04247E983228245B402E0188376DB1710EE0DB6",
      "algorithm": "sha256"
    },
    {
      "id": "github_release/github.com/bufbuild/buf/v1.57.0/buf-Linux-aarch64.tar.gz",
      "checksum": "69BCF037A7206433064AEE2307A9A1E99FC98F11967E311AB8D96EB55444C448",
      "algorithm": "sha256"
    },
    {
      "id": "github_release/github.com/bufbuild/buf/v1.57.0/buf-Linux-x86_64.tar.gz",
      "checksum": "2EAF200CD4C3D2DBBECE153597BF1382743D2046A8283E930E59EFF5A230FD0F",
      "algorithm": "sha256"
    },
    {
      "id": "github_release/github.com/bufbuild/buf/v1.57.0/buf-Windows-arm64.exe",
      "checksum": "B4862391FA93FCA4F589198E9631CEEF83999E569A5EF1FE226406AA46AFA2E3",
      "algorithm": "sha256"
    },
    {
      "id": "github_release/github.com/bufbuild/buf/v1.57.0/buf-Windows-x86_64.exe",
      "checksum": "6BD4ED4BD0E94BCE22027226A9B9225609696625B4C990B6FEE7A658B38A35D1",
      "algorithm": "sha256"
    },
    {
      "id": "github_release/github.com/cli/cli/v2.79.0/gh_2.79.0_linux_amd64.tar.gz",
      "checksum": "E7AF0C72A607C0528FDA1989F7C8E3BE85E67D321889002AF0E2938AD9C8FB68",
      "algorithm": "sha256"
    },
    {
      "id": "github_release/github.com/cli/cli/v2.79.0/gh_2.79.0_linux_arm64.tar.gz",
      "checksum": "1B91E546B30181A8EE6D8C72BBF59EAADBB0600BAB014DFBCC199676C83EA102",
      "algorithm": "sha256"
    },
    {
      "id": "github_release/github.com/cli/cli/v2.79.0/gh_2.79.0_macOS_amd64.zip",
      "checksum": "C1672616FCB3745A0E4285110143B1CC93C241BD867BF108084DEFDEA3D49331",
      "algorithm": "sha256"
    },
    {
      "id": "github_release/github.com/cli/cli/v2.79.0/gh_2.79.0_macOS_arm64.zip",
      "checksum": "5454F9509E3DBB8F321310E9E344877D9A01EBB8F8703886B1AFB0936D60FFAA",
      "algorithm": "sha256"
    },
    {
      "id": "github_release/github.com/cli/cli/v2.79.0/gh_2.79.0_windows_amd64.zip",
      "checksum": "0372DB012E22DB3D737ED592ED49B72FDCD47B46D7E9D7E75476410337BD278D",
      "algorithm": "sha256"
    },
    {
      "id": "github_release/github.com/cli/cli/v2.79.0/gh_2.79.0_windows_arm64.zip",
      "checksum": "EC5A7A926AFAEACBB0A0583E3AFA3275E4376CFB0AA73F8C3A045B291BB0D91D",
      "algorithm": "sha256"
    },
    {
      "id": "github_release/github.com/dandavison/delta/0.18.2/delta-0.18.2-aarch64-apple-darwin.tar.gz",
      "checksum": "6BA38DCE9F91EE1B9A24AA4AEDE1DB7195258FE176C3F8276AE2D4457D8170A0",
      "algorithm": "sha256"
    },
    {
      "id": "github_release/github.com/dandavison/delta/0.18.2/delta-0.18.2-aarch64-unknown-linux-gnu.tar.gz",
      "checksum": "ADF7674086DAA4582F598F74CE9CAA6B70C1BA8F4A57D2911499B37826B014F9",
      "algorithm": "sha256"
    },
    {
      "id": "github_release/github.com/dandavison/delta/0.18.2/delta-0.18.2-x86_64-apple-darwin.tar.gz",
      "checksum": "E9B5C4A9E73D2119C687E074F0D97F188E30E5FE8AE0E6D455755F74BB5CC0CF",
      "algorithm": "sha256"
    },
    {
      "id": "github_release/github.com/dandavison/delta/0.18.2/delta-0.18.2-x86_64-pc-windows-msvc.zip",
      "checksum": "6EA59864091B4CFCA89D9EE38388FF1A3CCDC8244B6E1CDD5201259DE89B0B06",
      "algorithm": "sha256"
    },
    {
      "id": "github_release/github.com/dandavison/delta/0.18.2/delta-0.18.2-x86_64-unknown-linux-musl.tar.gz",
      "checksum": "B7EA845004762358A00EF9127DD9FD723E333C7E4B9CB1DA220C3909372310EE",
      "algorithm": "sha256"
    },
    {
      "id": "github_release/github.com/denoland/deno/v2.5.0/deno-aarch64-apple-darwin.zip",
      "checksum": "DCC5F190ED80F021A9766FFD3EC9379D3B877752E18606CC30F7D2A07066798B",
      "algorithm": "sha256"
    },
    {
      "id": "github_release/github.com/denoland/deno/v2.5.0/deno-aarch64-unknown-linux-gnu.zip",
      "checksum": "81D2EF446954429F0DCBCB24CDCE115E5BB2C3A3548B79C01B49EC959682AC9B",
      "algorithm": "sha256"
    },
    {
      "id": "github_release/github.com/denoland/deno/v2.5.0/deno-x86_64-apple-darwin.zip",
      "checksum": "7B81603C8219A7FF034DEF4C1B1D04A25B27F5BF2388265F0D32A8C137D5AB95",
      "algorithm": "sha256"
    },
    {
      "id": "github_release/github.com/denoland/deno/v2.5.0/deno-x86_64-pc-windows-msvc.zip",
      "checksum": "EFBBDCDF4B97E89C13BFAB1B52E259FBAF73A38CCDCA4F132ECB6A500DE06F6D",
      "algorithm": "sha256"
    },
    {
      "id": "github_release/github.com/denoland/deno/v2.5.0/deno-x86_64-unknown-linux-gnu.zip",
      "checksum": "4561ADB06B13F287A3785276CB29F377B7FFB49D54290178223B037E161446D3",
      "algorithm": "sha256"
    },
    {
      "id": "github_release/github.com/direnv/direnv/v2.37.1/direnv.darwin-amd64",
      "checksum": "24FB9CE48B563D7E9FBDD3A4E3E836941654A31CE3E67EBA9EAAFC3DCD8AE73B",
      "algorithm": "sha256"
    },
    {
      "id": "github_release/github.com/direnv/direnv/v2.37.1/direnv.darwin-arm64",
      "checksum": "4F569F3A36732BFD8B8FEA7BFCC6AD87A59745C109022164D0CA4832451D5369",
      "algorithm": "sha256"
    },
    {
      "id": "github_release/github.com/direnv/direnv/v2.37.1/direnv.linux-amd64",
      "checksum": "1F1B93DD6F38523FDE26DFAC96151EF9D31A374E3005CD3345FB93555AE0C9B5",
      "algorithm": "sha256"
    },
    {
      "id": "github_release/github.com/direnv/direnv/v2.37.1/direnv.linux-arm64",
      "checksum": "2A9CEF8D73521D6A3EC3F2871C4B747B8C4CC038628C1B57A7EFA42B393A2D82",
      "algorithm": "sha256"
    },
    {
      "id": "github_release/github.com/direnv/direnv/v2.37.1/direnv.windows-amd64",
      "checksum": "D96FC8B7CF020C2D4C1DBBC2CCEC5FD1CAB05B51C491F02C8527A7FA6C50A1CD",
      "algorithm": "sha256"
    },
    {
      "id": "github_release/github.com/direnv/direnv/v2.37.1/direnv.windows-arm64",
      "checksum": "6802F722F5EF12562D6E3E15C26F39E34B337E5BE12EA22F17284552CD782298",
      "algorithm": "sha256"
    },
    {
      "id": "github_release/github.com/eza-community/eza/v0.23.3/eza.exe_x86_64-pc-windows-gnu.tar.gz",
      "checksum": "0A2DF426DD8BF7B9697C631AE96AF2D52641EE4DAA8FB07863C82E77BE5480A2",
      "algorithm": "sha256"
    },
    {
      "id": "github_release/github.com/eza-community/eza/v0.23.3/eza_aarch64-unknown-linux-gnu.tar.gz",
      "checksum": "333246365F1A3325DF1068FF8BC994EA3A3E04ABE4E118FA11015D589C5CC41D",
      "algorithm": "sha256"
    },
    {
      "id": "github_release/github.com/eza-community/eza/v0.23.3/eza_x86_64-unknown-linux-musl.tar.gz",
      "checksum": "9394077C94CED5A39B895092A4E59B21C3949B414A1AFFB08C47BE6A3AF17ECA",
      "algorithm": "sha256"
    },
    {
      "id": "github_release/github.com/github/github-mcp-server/v0.15.0/github-mcp-server_Darwin_arm64.tar.gz",
      "checksum": "96EEEF3F477323E4F52D79D4EC67A0828FF3E62783C04053D52488277545FFA0",
      "algorithm": "sha256"
    },
    {
      "id": "github_release/github.com/github/github-mcp-server/v0.15.0/github-mcp-server_Darwin_x86_64.tar.gz",
      "checksum": "5957BA8638CB1BCA8E5E27D37C5A6B7C611C6E29DCFADC4E157E382A0F555ED2",
      "algorithm": "sha256"
    },
    {
      "id": "github_release/github.com/github/github-mcp-server/v0.15.0/github-mcp-server_Linux_arm64.tar.gz",
      "checksum": "857F3009DAFC3310064C6294D39783C2F05E1956AA9AC93002C8F59F244B7948",
      "algorithm": "sha256"
    },
    {
      "id": "github_release/github.com/github/github-mcp-server/v0.15.0/github-mcp-server_Linux_x86_64.tar.gz",
      "checksum": "14B72EE93F2ADFBE330BE116BC2387845AB2C46B9E686E5659214D7FE75A422B",
      "algorithm": "sha256"
    },
    {
      "id": "github_release/github.com/github/github-mcp-server/v0.15.0/github-mcp-server_Windows_arm64.zip",
      "checksum": "5D24A2AB57A4DFC401928279013888A62DC23DB0D401CA117F367F66C5EC4D1B",
      "algorithm": "sha256"
    },
    {
      "id": "github_release/github.com/github/github-mcp-server/v0.15.0/github-mcp-server_Windows_x86_64.zip",
      "checksum": "B1ACA59602B6E703B3166CEB7C54429F346AE9D3F40B9FFDF5273DE33F563E4D",
      "algorithm": "sha256"
    },
    {
      "id": "github_release/github.com/golangci/golangci-lint/v1.64.8/golangci-lint-1.64.8-darwin-amd64.tar.gz",
      "checksum": "B52AEBB8CB51E00BFD5976099083FBE2C43EF556CEF9C87E58A8AE656E740444",
      "algorithm": "sha256"
    },
    {
      "id": "github_release/github.com/golangci/golangci-lint/v1.64.8/golangci-lint-1.64.8-darwin-arm64.tar.gz",
      "checksum": "70543D21E5B02A94079BE8AA11267A5B060865583E337FE768D39B5D3E2FAF1F",
      "algorithm": "sha256"
    },
    {
      "id": "github_release/github.com/golangci/golangci-lint/v1.64.8/golangci-lint-1.64.8-linux-amd64.tar.gz",
      "checksum": "B6270687AFB143D019F387C791CD2A6F1CB383BE9B3124D241CA11BD3CE2E54E",
      "algorithm": "sha256"
    },
    {
      "id": "github_release/github.com/golangci/golangci-lint/v1.64.8/golangci-lint-1.64.8-linux-arm64.tar.gz",
      "checksum": "A6AB58EBCB1C48572622146CDAEC2956F56871038A54ED1149F1386E287789A5",
      "algorithm": "sha256"
    },
    {
      "id": "github_release/github.com/golangci/golangci-lint/v1.64.8/golangci-lint-1.64.8-windows-amd64.zip",
      "checksum": "54C2ED3A6B4F2F5DA1056FB6E83D6B73B592E06684B65A5999174FABBB251A8F",
      "algorithm": "sha256"
    },
    {
      "id": "github_release/github.com/golangci/golangci-lint/v1.64.8/golangci-lint-1.64.8-windows-arm64.zip",
      "checksum": "24294BC46BC887691C7A43C66448F1DF9203C0A9C15BCB114B6147AA97973505",
      "algorithm": "sha256"
    },
    {
      "id": "github_release/github.com/grafana/jsonnet-language-server/v0.16.0/jsonnet-language-server_0.16.0_darwin_amd64",
      "checksum": "F37D57FCF851E18FECC3B3867A8E06305EE315E01A9430BF5448438EFF86736C",
      "algorithm": "sha256"
    },
    {
      "id": "github_release/github.com/grafana/jsonnet-language-server/v0.16.0/jsonnet-language-server_0.16.0_darwin_arm64",
      "checksum": "8B6E642374D3004C3AC35254874ED1D14203A85C979F6684FC6218F58A8072D4",
      "algorithm": "sha256"
    },
    {
      "id": "github_release/github.com/grafana/jsonnet-language-server/v0.16.0/jsonnet-language-server_0.16.0_linux_amd64",
      "checksum": "42C7D38515E5A2008DE26D678140E2D7FD1825EB977D78023FE997913E3DC2BE",
      "algorithm": "sha256"
    },
    {
      "id": "github_release/github.com/grafana/jsonnet-language-server/v0.16.0/jsonnet-language-server_0.16.0_linux_arm64",
      "checksum": "155933CBBDA25E9D89B6E14F1C2C52089CDFE82700FDA60D8EBAABAD2C409F18",
      "algorithm": "sha256"
    },
    {
      "id": "github_release/github.com/grafana/jsonnet-language-server/v0.16.0/jsonnet-language-server_0.16.0_windows_amd64.exe",
      "checksum": "53D233A1927AFA52F39A2AE5396DC7FFEB13283B5F13EDFA6DFDC1F41E71199B",
      "algorithm": "sha256"
    },
    {
      "id": "github_release/github.com/grafana/jsonnet-language-server/v0.16.0/jsonnet-language-server_0.16.0_windows_arm64.exe",
      "checksum": "8DAC64BB1E1F215988E3EA8FD2FBFE575251E3B07BA95E9BE3BC3EA3175E3522",
      "algorithm": "sha256"
    },
    {
      "id": "github_release/github.com/hadolint/hadolint/v2.13.1/hadolint-linux-arm64",
      "checksum": "CA77A6010454826AB90335095ADD1B9B84F2D72D44581B6C2DBE08CEC46B0165",
      "algorithm": "sha256"
    },
    {
      "id": "github_release/github.com/hadolint/hadolint/v2.13.1/hadolint-linux-x86_64",
      "checksum": "F8B05E4C724CDEB84C0DCA07E40936C3D875C0AF5D120A27C94026A0F370B2CF",
      "algorithm": "sha256"
    },
    {
      "id": "github_release/github.com/hadolint/hadolint/v2.13.1/hadolint-macos-arm64",
      "checksum": "0A3EB44BB5E496184DBEA71BE142A9BE8D70C11B48302AE851E6274EF09AE407",
      "algorithm": "sha256"
    },
    {
      "id": "github_release/github.com/hadolint/hadolint/v2.13.1/hadolint-macos-x86_64",
      "checksum": "D39DE79513B8BE68BD807664F1FC9FE328D95977EBA996E2D7BDA2BFEEAE753A",
      "algorithm": "sha256"
    },
    {
      "id": "github_release/github.com/hadolint/hadolint/v2.13.1/hadolint-windows-x86_64.exe",
      "checksum": "397BCB18F76F6C112A5E0D3B3579BA8ADF9E2EF71596387DF7DFDBE5C06E0E53",
      "algorithm": "sha256"
    },
    {
      "id": "github_release/github.com/jesseduffield/lazydocker/v0.24.1/lazydocker_0.24.1_Darwin_arm64.tar.gz",
      "checksum": "55D8FF53D9BD36EE088393154442D3B93DB787118BE5AD0AE80C200D76311EC2",
      "algorithm": "sha256"
    },
    {
      "id": "github_release/github.com/jesseduffield/lazydocker/v0.24.1/lazydocker_0.24.1_Darwin_x86_64.tar.gz",
      "checksum": "7B4C73C7B1B62B9702A701AC0A8A1D8913602173362E8EE96D4FC03EF556AD10",
      "algorithm": "sha256"
    },
    {
      "id": "github_release/github.com/jesseduffield/lazydocker/v0.24.1/lazydocker_0.24.1_Linux_arm64.tar.gz",
      "checksum": "C38E715F2CB56440BEC16E3744005522C1D13C47D2E3730572849DC69CEFD8AE",
      "algorithm": "sha256"
    },
    {
      "id": "github_release/github.com/jesseduffield/lazydocker/v0.24.1/lazydocker_0.24.1_Linux_x86_64.tar.gz",
      "checksum": "461CACF618E1020DFF1D7896248C1C1F2267D5C25FB529755E4B9C43C5D1D4A5",
      "algorithm": "sha256"
    },
    {
      "id": "github_release/github.com/jesseduffield/lazydocker/v0.24.1/lazydocker_0.24.1_Windows_arm64.zip",
      "checksum": "8D965FF79409802FF620F744F91CB932BE52B25C2A5ED7AA5131387645151EB8",
      "algorithm": "sha256"
    },
    {
      "id": "github_release/github.com/jesseduffield/lazydocker/v0.24.1/lazydocker_0.24.1_Windows_x86_64.zip",
      "checksum": "CC54494D8CD9232D8D64CF4C2D720A045E5B969A716739424702577F55B53CF9",
      "algorithm": "sha256"
    },
    {
      "id": "github_release/github.com/jesseduffield/lazygit/v0.55.0/lazygit_0.55.0_darwin_arm64.tar.gz",
      "checksum": "A3679901C0618C906424C0F9CF49ABB4B687B2C610F47FF344420B9A494BECF4",
      "algorithm": "sha256"
    },
    {
      "id": "github_release/github.com/jesseduffield/lazygit/v0.55.0/lazygit_0.55.0_darwin_x86_64.tar.gz",
      "checksum": "4114A044F8323B0BD2224841536103D7C6B63DDBB589242A336EB34D4CA615CF",
      "algorithm": "sha256"
    },
    {
      "id": "github_release/github.com/jesseduffield/lazygit/v0.55.0/lazygit_0.55.0_linux_arm64.tar.gz",
      "checksum": "6730250C140CD02E464F3E49B838DEB4422EE61ADA3227D4D88BD23FA881B8F0",
      "algorithm": "sha256"
    },
    {
      "id": "github_release/github.com/jesseduffield/lazygit/v0.55.0/lazygit_0.55.0_linux_x86_64.tar.gz",
      "checksum": "E7C1C2D127EBDB241398F3DAF05907A71A0C977FF12BEBA6B8EBDB069F9DBA6A",
      "algorithm": "sha256"
    },
    {
      "id": "github_release/github.com/jesseduffield/lazygit/v0.55.0/lazygit_0.55.0_windows_arm64.zip",
      "checksum": "0302426DE46B45198C2070CCEB9F24F8D402AE0BD61203AC7D6D06569976D806",
      "algorithm": "sha256"
    },
    {
      "id": "github_release/github.com/jesseduffield/lazygit/v0.55.0/lazygit_0.55.0_windows_x86_64.zip",
      "checksum": "E0ADB62EB2FF619DBC2F1596FE469E1E31325541317637215882A0BF6332B87F",
      "algorithm": "sha256"
    },
    {
      "id": "github_release/github.com/jqlang/jq/jq-1.8.1/jq-linux-amd64",
      "checksum": "020468DE7539CE70EF1BCEAF7CDE2E8C4F2CA6C3AFB84642AABC5C97D9FC2A0D",
      "algorithm": "sha256"
    },
    {
      "id": "github_release/github.com/jqlang/jq/jq-1.8.1/jq-linux-arm64",
      "checksum": "6BC62F25981328EDD3CFCFE6FE51B073F2D7E7710D7EF7FCDAC28D4E384FC3D4",
      "algorithm": "sha256"
    },
    {
      "id": "github_release/github.com/jqlang/jq/jq-1.8.1/jq-macos-amd64",
      "checksum": "E80DBE0D2A2597E3C11C404F03337B981D74B4A8504B70586C354B7697A7C27F",
      "algorithm": "sha256"
    },
    {
      "id": "github_release/github.com/jqlang/jq/jq-1.8.1/jq-macos-arm64",
      "checksum": "A9FE3EA2F86DFC72F6728417521EC9067B343277152B114F4E98D8CB0E263603",
      "algorithm": "sha256"
    },
    {
      "id": "github_release/github.com/jqlang/jq/jq-1.8.1/jq-windows-amd64.exe",
      "checksum": "23CB60A1354EED6BCC8D9B9735E8C7B388CD1FDCB75726B93BC299EF22DD9334",
      "algorithm": "sha256"
    },
    {
      "id": "github_release/github.com/junegunn/fzf/v0.65.2/fzf-0.65.2-darwin_amd64.tar.gz",
      "checksum": "4F2D7414E4DBE2469E5581C5830F29B1ED3532A3D672646E6C2E0533FC07CBEA",
      "algorithm": "sha256"
    },
    {
      "id": "github_release/github.com/junegunn/fzf/v0.65.2/fzf-0.65.2-darwin_arm64.tar.gz",
      "checksum": "A1464F1D4B75C3A92975F67055F9E407800ED35820EA7D73F2AFB90AEB0491E8",
      "algorithm": "sha256"
    },
    {
      "id": "github_release/github.com/junegunn/fzf/v0.65.2/fzf-0.65.2-linux_amd64.tar.gz",
      "checksum": "5EB8EFC0E94AA559F84EA83EEBA99BEA7DCE818E63F92B4B62E60663220F1C14",
      "algorithm": "sha256"
    },
    {
      "id": "github_release/github.com/junegunn/fzf/v0.65.2/fzf-0.65.2-linux_arm64.tar.gz",
      "checksum": "097347160595BF03A426D2ABE0A17E14CA060540DDFC0EA45C0A9BE62BB29A2B",
      "algorithm": "sha256"
    },
    {
      "id": "github_release/github.com/junegunn/fzf/v0.65.2/fzf-0.65.2-windows_amd64.zip",
      "checksum": "AD77A1E4B6EA6B790B02BFAD333EB3E2A802E5E5423271733B324794EDA31B9E",
      "algorithm": "sha256"
    },
    {
      "id": "github_release/github.com/junegunn/fzf/v0.65.2/fzf-0.65.2-windows_arm64.zip",
      "checksum": "FA15B9DA97C1BABCAB7D6E2992045F9237AAA06A13498CD78FA0367558F003A3",
      "algorithm": "sha256"
    },
    {
      "id": "github_release/github.com/mvdan/sh/v3.12.0/shfmt_v3.12.0_darwin_amd64",
      "checksum": "C31548693DE6584E6164B7ED5FBB7B4A083F2D937CA94B4E0DDF59AA461A85E4",
      "algorithm": "sha256"
    },
    {
      "id": "github_release/github.com/mvdan/sh/v3.12.0/shfmt_v3.12.0_darwin_arm64",
      "checksum": "D903802E0CE3ECBC82B98512F55BA370B0D37A93F3F78DE394F5B657052B33DD",
      "algorithm": "sha256"
    },
    {
      "id": "github_release/github.com/mvdan/sh/v3.12.0/shfmt_v3.12.0_linux_amd64",
      "checksum": "D9FBB2A9C33D13F47E7618CF362A914D029D02A6DF124064FFF04FD688A745EA",
      "algorithm": "sha256"
    },
    {
      "id": "github_release/github.com/mvdan/sh/v3.12.0/shfmt_v3.12.0_linux_arm64",
      "checksum": "5F3FE3FA6A9F766E6A182BA79A94BEF8AFEDAFC57DB0B1AD32B0F67FAE971BA4",
      "algorithm": "sha256"
    },
    {
      "id": "github_release/github.com/mvdan/sh/v3.12.0/shfmt_v3.12.0_windows_amd64.exe",
      "checksum": "C8BDA517BA1C640CE4A715C0FA665439DDBE4357BA5E9B77B0E51E70E2B9C94B",
      "algorithm": "sha256"
    },
    {
      "id": "github_release/github.com/nametake/golangci-lint-langserver/v0.0.11/golangci-lint-langserver_Darwin_arm64.tar.gz",
      "checksum": "D9F704E6AE3BA63B8F452DFEC3C9B2B418652AD3BA3A1D0B92AE70FD2C74D2B1",
      "algorithm": "sha256"
    },
    {
      "id": "github_release/github.com/nametake/golangci-lint-langserver/v0.0.11/golangci-lint-langserver_Darwin_x86_64.tar.gz",
      "checksum": "FA6629E251FD7F82E330FF85D3E63AF3D1986374AD538A6A26D4A855B3E3009F",
      "algorithm": "sha256"
    },
    {
      "id": "github_release/github.com/nametake/golangci-lint-langserver/v0.0.11/golangci-lint-langserver_Linux_arm64.tar.gz",
      "checksum": "7D3695A366E653569A375D209516B3FA8CA184B92FC5ACBFEDFAEE9AD3C97C21",
      "algorithm": "sha256"
    },
    {
      "id": "github_release/github.com/nametake/golangci-lint-langserver/v0.0.11/golangci-lint-langserver_Linux_x86_64.tar.gz",
      "checksum": "B4EFA95267C29CA4D08E0A977E90E7C6A8A606BAFE1DCEDFD5E48E952536B331",
      "algorithm": "sha256"
    },
    {
      "id": "github_release/github.com/nametake/golangci-lint-langserver/v0.0.11/golangci-lint-langserver_Windows_arm64.zip",
      "checksum": "4DEEF94143C5C45D9513B7D1507B118FC989D360612FB440811CFFD39028E872",
      "algorithm": "sha256"
    },
    {
      "id": "github_release/github.com/nametake/golangci-lint-langserver/v0.0.11/golangci-lint-langserver_Windows_x86_64.zip",
      "checksum": "6A4620EE48D94406BA1E0E986D4F9F1D926BBAB2212B3F5D9D106F80A67A3037",
      "algorithm": "sha256"
    },
    {
      "id": "github_release/github.com/neovim/neovim/v0.11.4/nvim-linux-arm64.tar.gz",
      "checksum": "684E4262D2296E469CB43F0D05EDBBB52B960B7F117BED6B22936FC768993CD9",
      "algorithm": "sha256"
    },
    {
      "id": "github_release/github.com/neovim/neovim/v0.11.4/nvim-linux-x86_64.tar.gz",
      "checksum": "A74740047E73B2B380D63A474282814063D10650CD6CC95EFA16D1713C7E616C",
      "algorithm": "sha256"
    },
    {
      "id": "github_release/github.com/neovim/neovim/v0.11.4/nvim-macos-arm64.tar.gz",
      "checksum": "2DE9623A4AA8CEDF85C51E33BF8E85E05F6F291B923CD666C04704CCF164E8B7",
      "algorithm": "sha256"
    },
    {
      "id": "github_release/github.com/neovim/neovim/v0.11.4/nvim-macos-x86_64.tar.gz",
      "checksum": "567B89138C29386F67A00FC8E26C6469C8BF0E5707DFEA5E3FBAF4E21294D9EB",
      "algorithm": "sha256"
    },
    {
      "id": "github_release/github.com/neovim/neovim/v0.11.4/nvim-win64.zip",
      "checksum": "77EEE5936724B82E45B448E0370ABE0911D75FAD551C0A25415F4E51719FAF34",
      "algorithm": "sha256"
    },
    {
      "id": "github_release/github.com/pnpm/pnpm/v10.16.1/pnpm-linux-arm64",
      "checksum": "D7AC57834C87520455F92043FC825F0AC68E9D116A32B7445A8BC72A11263F01",
      "algorithm": "sha256"
    },
    {
      "id": "github_release/github.com/pnpm/pnpm/v10.16.1/pnpm-linux-x64",
      "checksum": "314E21C7CB2915EDDFE7C4D66E891BB41F3FC641A19819BCBE1E6A71FCFB5E94",
      "algorithm": "sha256"
    },
    {
      "id": "github_release/github.com/pnpm/pnpm/v10.16.1/pnpm-macos-arm64",
      "checksum": "630468B2B24925F2C27D1802697EA0A8EB7DBE9C551C02181E8D7F2845B997A5",
      "algorithm": "sha256"
    },
    {
      "id": "github_release/github.com/pnpm/pnpm/v10.16.1/pnpm-macos-x64",
      "checksum": "B3E2B62B3CDF1AC89756E5DA7262EAB33864354147C8EB256B942F85E740CC04",
      "algorithm": "sha256"
    },
    {
      "id": "github_release/github.com/pnpm/pnpm/v10.16.1/pnpm-win-x64.exe",
      "checksum": "EEBB1DE6D9A00CBB9D5CABEA9F90B0E1101EFEC6EFD175BBFF44B285AF6F7531",
      "algorithm": "sha256"
    },
    {
      "id": "github_release/github.com/rhysd/actionlint/v1.7.7/actionlint_1.7.7_darwin_amd64.tar.gz",
      "checksum": "28E5DE5A05FC558474F638323D736D822FFF183D2D492F0AECB2B73CC44584F5",
      "algorithm": "sha256"
    },
    {
      "id": "github_release/github.com/rhysd/actionlint/v1.7.7/actionlint_1.7.7_darwin_arm64.tar.gz",
      "checksum": "2693315B9093AEACB4EBD91A993FEA54FC215057BF0DA2659056B4BC033873DB",
      "algorithm": "sha256"
    },
    {
      "id": "github_release/github.com/rhysd/actionlint/v1.7.7/actionlint_1.7.7_linux_amd64.tar.gz",
      "checksum": "023070A287CD8CCCD71515FEDC843F1985BF96C436B7EFFAECCE67290E7E0757",
      "algorithm": "sha256"
    },
    {
      "id": "github_release/github.com/rhysd/actionlint/v1.7.7/actionlint_1.7.7_linux_arm64.tar.gz",
      "checksum": "401942F9C24ED71E4FE71B76C7D638F66D8633575C4016EFD2977CE7C28317D0",
      "algorithm": "sha256"
    },
    {
      "id": "github_release/github.com/rhysd/actionlint/v1.7.7/actionlint_1.7.7_windows_amd64.zip",
      "checksum": "7F12F1801BCA3D480D67AAF7774F4C2A6359A3CA8EEBE382C95C10C9704AA731",
      "algorithm": "sha256"
    },
    {
      "id": "github_release/github.com/rhysd/actionlint/v1.7.7/actionlint_1.7.7_windows_arm64.zip",
      "checksum": "76E9514CFAC18E5677AA04F3A89873C981F16A2F2353BB97372A86CD09B1F5A8",
      "algorithm": "sha256"
    },
    {
      "id": "github_release/github.com/rossmacarthur/sheldon/0.8.5/sheldon-0.8.5-aarch64-apple-darwin.tar.gz",
      "checksum": "6E47F10A25F165B095EB2BDE1AB617D4D34AD6F3FF2CA984167CA94FADD52730",
      "algorithm": "sha256"
    },
    {
      "id": "github_release/github.com/rossmacarthur/sheldon/0.8.5/sheldon-0.8.5-aarch64-unknown-linux-musl.tar.gz",
      "checksum": "1F6B792E49E259F7C313E9921C8D4AD638D827ABC2C023EFE0588A55678F9A3E",
      "algorithm": "sha256"
    },
    {
      "id": "github_release/github.com/rossmacarthur/sheldon/0.8.5/sheldon-0.8.5-x86_64-unknown-linux-musl.tar.gz",
      "checksum": "80AA0BE617072C278D67FD6C5FBCE4903D3801D78B6ABF8F058F0648D2242C78",
      "algorithm": "sha256"
    },
    {
      "id": "github_release/github.com/sharkdp/bat/v0.25.0/bat-v0.25.0-aarch64-apple-darwin.tar.gz",
      "checksum": "B3ED5A7515545445881F1036F0CC1B708C2B86CBCE01C1B4033F38E0CFCC7B3C",
      "algorithm": "sha256"
    },
    {
      "id": "github_release/github.com/sharkdp/bat/v0.25.0/bat-v0.25.0-aarch64-unknown-linux-musl.tar.gz",
      "checksum": "EE0F12CF6006A79CF4CCF75D2DDCF9F6BA124644503244B1AF909C2F72A2A9F7",
      "algorithm": "sha256"
    },
    {
      "id": "github_release/github.com/sharkdp/bat/v0.25.0/bat-v0.25.0-x86_64-apple-darwin.tar.gz",
      "checksum": "B974AA834B6B65610090AED2BC7310D11C6F500105696D23A130AEE24FD8380F",
      "algorithm": "sha256"
    },
    {
      "id": "github_release/github.com/sharkdp/bat/v0.25.0/bat-v0.25.0-x86_64-pc-windows-msvc.zip",
      "checksum": "1D5CED071BA9C765E16F4065877C178CEFCFD2FE9581E9DDC92AF265B73991BD",
      "algorithm": "sha256"
    },
    {
      "id": "github_release/github.com/sharkdp/bat/v0.25.0/bat-v0.25.0-x86_64-unknown-linux-musl.tar.gz",
      "checksum": "93F47D76ABE328C402EF712E9AC92AA6D5BC84D5ADCBCAF0BBC5665E5275A941",
      "algorithm": "sha256"
    },
    {
      "id": "github_release/github.com/sharkdp/fd/v10.3.0/fd-v10.3.0-aarch64-apple-darwin.tar.gz",
      "checksum": "0570263812089120BC2A5D84F9E65CD0C25E4A4D724C80075C357239C74AE904",
      "algorithm": "sha256"
    },
    {
      "id": "github_release/github.com/sharkdp/fd/v10.3.0/fd-v10.3.0-aarch64-unknown-linux-musl.tar.gz",
      "checksum": "996B9B1366433B211CB3BBEDBA91C9DBCE2431842144D925428EAD0ADF32020B",
      "algorithm": "sha256"
    },
    {
      "id": "github_release/github.com/sharkdp/fd/v10.3.0/fd-v10.3.0-x86_64-apple-darwin.tar.gz",
      "checksum": "50D30F13FE3D5914B14C4FFF5ABCBD4D0CDAB4B855970A6956F4F006C17117A3",
      "algorithm": "sha256"
    },
    {
      "id": "github_release/github.com/sharkdp/fd/v10.3.0/fd-v10.3.0-x86_64-pc-windows-msvc.zip",
      "checksum": "318AA2A6FA664325933E81FDA60D523FFF29444129E91EBF0726B5B3BCD8B059",
      "algorithm": "sha256"
    },
    {
      "id": "github_release/github.com/sharkdp/fd/v10.3.0/fd-v10.3.0-x86_64-unknown-linux-musl.tar.gz",
      "checksum": "2B6BFAAE8C48F12050813C2FFE1884C61EA26E750D803DF9C9114550A314CD14",
      "algorithm": "sha256"
    },
    {
      "id": "github_release/github.com/starship/starship/v1.23.0/starship-aarch64-apple-darwin.tar.gz",
      "checksum": "042C8001275316836A3C43FDB88D0787395EDFD0C10D209E4892AB5577B80D57",
      "algorithm": "sha256"
    },
    {
      "id": "github_release/github.com/starship/starship/v1.23.0/starship-aarch64-pc-windows-msvc.zip",
      "checksum": "B89470C308FA2FA4BF77D0DF8EA9C74D8102817BE936B2367959845C60008BAA",
      "algorithm": "sha256"
    },
    {
      "id": "github_release/github.com/starship/starship/v1.23.0/starship-aarch64-unknown-linux-musl.tar.gz",
      "checksum": "D37040138C68B5F3334BBE16D4615F0A83829DEEBECC5D014E779C302E8270D8",
      "algorithm": "sha256"
    },
    {
      "id": "github_release/github.com/starship/starship/v1.23.0/starship-x86_64-apple-darwin.tar.gz",
      "checksum": "8CAC7A18FB1FAF0AEC50BD221DD71ECC8553850D99C212231851AE64BA11F089",
      "algorithm": "sha256"
    },
    {
      "id": "github_release/github.com/starship/starship/v1.23.0/starship-x86_64-pc-windows-msvc.zip",
      "checksum": "50E670DDA19BCC480AE4D1F7F0D3C7A092693252292406B54ABABA706100F03C",
      "algorithm": "sha256"
    },
    {
      "id": "github_release/github.com/starship/starship/v1.23.0/starship-x86_64-unknown-linux-musl.tar.gz",
      "checksum": "8D06D2CC67AEDD6316FF58AB679FB80CDED0D85DE1DCD5727DF0633D35356D57",
      "algorithm": "sha256"
    },
    {
      "id": "github_release/github.com/stripe/stripe-cli/v1.30.0/stripe_1.30.0_linux_arm64.tar.gz",
      "checksum": "8968CC15872E3733B769481B4BF1D3DF54672373F34C9D75DE115EDC93536E71",
      "algorithm": "sha256"
    },
    {
      "id": "github_release/github.com/stripe/stripe-cli/v1.30.0/stripe_1.30.0_linux_x86_64.tar.gz",
      "checksum": "6B6CCCE79E73819E4CA7A0F23227FB730E04D6C11FA948A079DE18C70544BE91",
      "algorithm": "sha256"
    },
    {
      "id": "github_release/github.com/stripe/stripe-cli/v1.30.0/stripe_1.30.0_mac-os_arm64.tar.gz",
      "checksum": "22A72BBB0F463B41B63FD6FCBD2893838956D09FEF6776C4A7671870A938EA43",
      "algorithm": "sha256"
    },
    {
      "id": "github_release/github.com/stripe/stripe-cli/v1.30.0/stripe_1.30.0_mac-os_x86_64.tar.gz",
      "checksum": "277173D37A273EE6BE033FA3E894BE33DC68E93DE35EECC076ABABC7DFDAD245",
      "algorithm": "sha256"
    },
    {
      "id": "github_release/github.com/stripe/stripe-cli/v1.30.0/stripe_1.30.0_windows_x86_64.zip",
      "checksum": "5A4F33B9D3CF4E7852FD7B841086461AC1618B05376FE9C09F68AD8F5CD9A27E",
      "algorithm": "sha256"
    },
    {
      "id": "github_release/github.com/x-motemen/ghq/v1.8.0/ghq_darwin_amd64.zip",
      "checksum": "742A64C85B7C01A1399AE286E886CFFC4649EE38891FB01CD32F31394610EA80",
      "algorithm": "sha256"
    },
    {
      "id": "github_release/github.com/x-motemen/ghq/v1.8.0/ghq_darwin_arm64.zip",
      "checksum": "0399A4DCDDEEB9E76F7F9EEB8015F91A6F093B04C14D3EB87EB563E5D94F9B0A",
      "algorithm": "sha256"
    },
    {
      "id": "github_release/github.com/x-motemen/ghq/v1.8.0/ghq_linux_amd64.zip",
      "checksum": "AD0EC7B2F52312DCA85F35B5C9E88A77447C2C71BABBD9DFEB569AB369B8E55F",
      "algorithm": "sha256"
    },
    {
      "id": "github_release/github.com/x-motemen/ghq/v1.8.0/ghq_linux_arm64.zip",
      "checksum": "982A8D0F832664B6D54A0C4089198414B97DCB33E5AED7897C5C0F0FC10E6806",
      "algorithm": "sha256"
    },
    {
      "id": "github_release/github.com/x-motemen/ghq/v1.8.0/ghq_windows_amd64.zip",
      "checksum": "F609538DD0A46987EEE933FFF8A1607DFB788DF7C396F2282821AE52BD3210BD",
      "algorithm": "sha256"
    },
    {
      "id": "github_release/github.com/x-motemen/ghq/v1.8.0/ghq_windows_arm64.zip",
      "checksum": "03E329E679B10A1B1A2C28A9BCB6D90AE9A39E273C0E8923071ABF8F72DB1C85",
      "algorithm": "sha256"
    },
    {
      "id": "http/awscli.amazonaws.com/AWSCLIV2-2.28.26.pkg",
      "checksum": "790A3E207C2A3574AB92AECF6122CFD0B067DEBCFE513AFF1F2911FD8E8B18D3",
      "algorithm": "sha256"
    },
    {
      "id": "http/awscli.amazonaws.com/awscli-exe-linux-aarch64-2.28.26.zip",
      "checksum": "78EF029CDD3E9122F9E6F1D52F1110A5BEEBDF82F9BD6FE4468A0E488EE91E86",
      "algorithm": "sha256"
    },
    {
      "id": "http/awscli.amazonaws.com/awscli-exe-linux-x86_64-2.28.26.zip",
      "checksum": "DF7B96A84F720BC418D3B2AD61CF3877AE336E651E1AA0B43879AF0D6F6ED028",
      "algorithm": "sha256"
    },
    {
      "id": "http/golang.org/dl/go1.25.1.darwin-amd64.tar.gz",
      "checksum": "1D622468F767A1B9FE1E1E67BD6CE6744D04E0C68712ADC689748BBECCB126BB",
      "algorithm": "sha256"
    },
    {
      "id": "http/golang.org/dl/go1.25.1.darwin-arm64.tar.gz",
      "checksum": "68DEEBB214F39D542E518EBB0598A406AB1B5A22BBA8EC9ADE9F55FB4DD94A6C",
      "algorithm": "sha256"
    },
    {
      "id": "http/golang.org/dl/go1.25.1.linux-amd64.tar.gz",
      "checksum": "7716A0D940A0F6AE8E1F3B3F4F36299DC53E31B16840DBD171254312C41CA12E",
      "algorithm": "sha256"
    },
    {
      "id": "http/golang.org/dl/go1.25.1.linux-arm64.tar.gz",
      "checksum": "65A3E34FB2126F55B34E1EDFC709121660E1BE2DEE6BDF405FC399A63A95A87D",
      "algorithm": "sha256"
    },
    {
      "id": "http/golang.org/dl/go1.25.1.windows-amd64.zip",
      "checksum": "4A974DE310E7EE1D523D2FCEDB114BA5FA75408C98EB3652023E55CCF3FA7CAB",
      "algorithm": "sha256"
    },
    {
      "id": "http/golang.org/dl/go1.25.1.windows-arm64.zip",
      "checksum": "04BC3C078E9E904C4D58D6AC2532A5BDD402BD36A9FF0B5949B3C5E6006A05EE",
      "algorithm": "sha256"
    },
    {
      "id": "registries/github_content/github.com/aquaproj/aqua-registry/v4.411.0/registry.yaml",
      "checksum": "BCCFE29BDC9CE9197794AC7395CBCCDA86AC30A096CA4FDAF8F60D777CE53DF76AC712CB683563FBA26D97B3CB103C7A3364A617B5EA2782848EE9495399303C",
      "algorithm": "sha512"
    }
  ]
}
