{
  "checksums": [
    {
      "id": "github_content/github.com/awslabs/git-secrets/1.3.0/git-secrets",
      "checksum": "DF9A5D2BEEDA1C83E23105F46EFE464BB4C97F8328E1E66754D7DAACFAF7272B",
      "algorithm": "sha256"
    },
    {
      "id": "github_release/github.com/BurntSushi/ripgrep/14.1.1/ripgrep-14.1.1-aarch64-apple-darwin.tar.gz",
      "checksum": "24AD76777745FBFF131C8FBC466742B011F925BFA4FFFA2DED6DEF23B5B937BE",
      "algorithm": "sha256"
    },
    {
      "id": "github_release/github.com/BurntSushi/ripgrep/14.1.1/ripgrep-14.1.1-aarch64-unknown-linux-gnu.tar.gz",
      "checksum": "C827481C4FF4EA10C9DC7A4022C8DE5DB34A5737CB74484D62EB94A95841AB2F",
      "algorithm": "sha256"
    },
    {
      "id": "github_release/github.com/BurntSushi/ripgrep/14.1.1/ripgrep-14.1.1-x86_64-apple-darwin.tar.gz",
      "checksum": "FC87E78F7CB3FEA12D69072E7EF3B21509754717B746368FD40D88963630E2B3",
      "algorithm": "sha256"
    },
    {
      "id": "github_release/github.com/BurntSushi/ripgrep/14.1.1/ripgrep-14.1.1-x86_64-pc-windows-msvc.zip",
      "checksum": "D0F534024C42AFD6CB4D38907C25CD2B249B79BBE6CC1DBEE8E3E37C2B6E25A1",
      "algorithm": "sha256"
    },
    {
      "id": "github_release/github.com/BurntSushi/ripgrep/14.1.1/ripgrep-14.1.1-x86_64-unknown-linux-musl.tar.gz",
      "checksum": "4CF9F2741E6C465FFDB7C26F38056A59E2A2544B51F7CC128EF28337EEAE4D8E",
      "algorithm": "sha256"
    },
    {
      "id": "github_release/github.com/JohnnyMorganz/StyLua/v2.0.2/stylua-linux-aarch64.zip",
      "checksum": "AD2F1B2BCB215CA3009310F8978AD14DB78057CEC1B4767B4F73CC7F3BA8047E",
      "algorithm": "sha256"
    },
    {
      "id": "github_release/github.com/JohnnyMorganz/StyLua/v2.0.2/stylua-linux-x86_64-musl.zip",
      "checksum": "A9E1436424414B73976DDC27FFDAAB61CDC18595F32A3A7F5C661E0F327E1BA7",
      "algorithm": "sha256"
    },
    {
      "id": "github_release/github.com/JohnnyMorganz/StyLua/v2.0.2/stylua-macos-aarch64.zip",
      "checksum": "126BE217B089755AF3C681D0597585136D181864470232899A6DE31F68BA16FD",
      "algorithm": "sha256"
    },
    {
      "id": "github_release/github.com/JohnnyMorganz/StyLua/v2.0.2/stylua-macos-x86_64.zip",
      "checksum": "4CB47D1C0131A19F7BDB8FC10D6347F038D4853EAA13D9970A8C611FA4731606",
      "algorithm": "sha256"
    },
    {
      "id": "github_release/github.com/JohnnyMorganz/StyLua/v2.0.2/stylua-windows-x86_64.zip",
      "checksum": "B88B32417A37AF623698FA4BA0BED9ABF3A777A2CBF532B4C4313D7EC9679AEE",
      "algorithm": "sha256"
    },
    {
      "id": "github_release/github.com/LuaLS/lua-language-server/3.13.9/lua-language-server-3.13.9-darwin-arm64.tar.gz",
      "checksum": "2AC04C39457A3D339876E88E0E0BAFF8183F610C48A5BFAE5C437A0AA2D3B289",
      "algorithm": "sha256"
    },
    {
      "id": "github_release/github.com/LuaLS/lua-language-server/3.13.9/lua-language-server-3.13.9-darwin-x64.tar.gz",
      "checksum": "14E4558A2B7BF27D81A78A0559F91113ABE73F01FC6CDE77B3CCCA713E3E22A7",
      "algorithm": "sha256"
    },
    {
      "id": "github_release/github.com/LuaLS/lua-language-server/3.13.9/lua-language-server-3.13.9-linux-arm64.tar.gz",
      "checksum": "0857343D82CDBC01CE2ED56B548358EC90C351F2D0DB28C567D1198D531018DF",
      "algorithm": "sha256"
    },
    {
      "id": "github_release/github.com/LuaLS/lua-language-server/3.13.9/lua-language-server-3.13.9-linux-x64.tar.gz",
      "checksum": "17642B2154446C0A15C7F6D335242F071D6910CE1E76C7CD95A29B64DFAE1348",
      "algorithm": "sha256"
    },
    {
      "id": "github_release/github.com/LuaLS/lua-language-server/3.13.9/lua-language-server-3.13.9-win32-x64.zip",
      "checksum": "27E1A8EE603F8CA0F7DB2B585AEE2A7720616B98A9107BD2631E9FC685BA3553",
      "algorithm": "sha256"
    },
    {
      "id": "github_release/github.com/Schniz/fnm/v1.38.1/fnm-arm64.zip",
      "checksum": "69FEDA9455931C26C84BE9F95F5E6F69E8B64686E68069FAB7CFC34756CD2944",
      "algorithm": "sha256"
    },
    {
      "id": "github_release/github.com/Schniz/fnm/v1.38.1/fnm-linux.zip",
      "checksum": "B69E5C9A05C1E17E4A7DE9A17DF14BA430D049F2591AF791A6F850A170296069",
      "algorithm": "sha256"
    },
    {
      "id": "github_release/github.com/Schniz/fnm/v1.38.1/fnm-macos.zip",
      "checksum": "80DEB3DB3DB45598F25AEA594C10936A7658F70826104FE37E33B4072A5E11F9",
      "algorithm": "sha256"
    },
    {
      "id": "github_release/github.com/Schniz/fnm/v1.38.1/fnm-windows.zip",
      "checksum": "377796E8F2F51EB8B5DE8983974CAA8922B83C167197B68B33962775703AD4A0",
      "algorithm": "sha256"
    },
    {
      "id": "github_release/github.com/Wilfred/difftastic/0.63.0/difft-x86_64-apple-darwin.tar.gz",
      "checksum": "90EBE77EE6392B43B6D04E266F61150531C353F869E0D3666451484E4CF73FBC",
      "algorithm": "sha256"
    },
    {
      "id": "github_release/github.com/Wilfred/difftastic/0.63.0/difft-x86_64-pc-windows-msvc.zip",
      "checksum": "033AE31243152CD47F88AD892B56A840A218414D5F279DE32374FF3A81F15119",
      "algorithm": "sha256"
    },
    {
      "id": "github_release/github.com/Wilfred/difftastic/0.63.0/difft-x86_64-unknown-linux-gnu.tar.gz",
      "checksum": "EF4C020D919CD8E1B5D6A69EAD14EE6846BA3C4CADDA5BAC7EF63B1A09B27535",
      "algorithm": "sha256"
    },
    {
      "id": "github_release/github.com/auth0/auth0-cli/v1.11.0/auth0-cli_1.11.0_Darwin_arm64.tar.gz",
      "checksum": "D271FBBAE04C1F7F9E5EF57E50A5B2F18EB6141F99933800AAB44345CD167D11",
      "algorithm": "sha256"
    },
    {
      "id": "github_release/github.com/auth0/auth0-cli/v1.11.0/auth0-cli_1.11.0_Darwin_x86_64.tar.gz",
      "checksum": "58845D73ECDB27AB7F5BA267ADB6878961C1C088DD55EC740182CF74862E6BFF",
      "algorithm": "sha256"
    },
    {
      "id": "github_release/github.com/auth0/auth0-cli/v1.11.0/auth0-cli_1.11.0_Linux_arm64.tar.gz",
      "checksum": "48F8ED688209718E10AD1667CA38E6BC913E86B31E8307E6785A34AA53F09D04",
      "algorithm": "sha256"
    },
    {
      "id": "github_release/github.com/auth0/auth0-cli/v1.11.0/auth0-cli_1.11.0_Linux_x86_64.tar.gz",
      "checksum": "D0B6196842236A5FAC0D06BA19D044FC3B28112C2A66C092015BBE376425F009",
      "algorithm": "sha256"
    },
    {
      "id": "github_release/github.com/auth0/auth0-cli/v1.11.0/auth0-cli_1.11.0_Windows_arm64.zip",
      "checksum": "7C5FB8B89B3544F2F994D8C064F0C731B4C946A58993E29254D64AFF565F4E41",
      "algorithm": "sha256"
    },
    {
      "id": "github_release/github.com/auth0/auth0-cli/v1.11.0/auth0-cli_1.11.0_Windows_x86_64.zip",
      "checksum": "A87A6017316B94BE37958524C1F655888D8F4A4459AC53ED295D2172CD71962E",
      "algorithm": "sha256"
    },
    {
      "id": "github_release/github.com/bufbuild/buf/v1.51.0/buf-Darwin-arm64.tar.gz",
      "checksum": "FC34097DDC95533B0D8065BDF9CF368C63F040EA9D96FFDA4AB2805122FDDBCE",
      "algorithm": "sha256"
    },
    {
      "id": "github_release/github.com/bufbuild/buf/v1.51.0/buf-Darwin-x86_64.tar.gz",
      "checksum": "ED5873B81F80D2AA95F4534B51C3A9E0D382D807902706B4AEE7A61BE5516461",
      "algorithm": "sha256"
    },
    {
      "id": "github_release/github.com/bufbuild/buf/v1.51.0/buf-Linux-aarch64.tar.gz",
      "checksum": "853F91722AB06E8E7D140B9693F6F6EAFD4812636F193AB5DBAE99EE1612F1B6",
      "algorithm": "sha256"
    },
    {
      "id": "github_release/github.com/bufbuild/buf/v1.51.0/buf-Linux-x86_64.tar.gz",
      "checksum": "3CF4AA139B289E09F76F3B506D0F48B5D27BD4A58B510AF6B976E6A0FB4A0953",
      "algorithm": "sha256"
    },
    {
      "id": "github_release/github.com/bufbuild/buf/v1.51.0/buf-Windows-arm64.exe",
      "checksum": "76F2BB83960ED0563440557E83D4FD8942F7F8201FB50EA9BB7DE4F3F81CF8A1",
      "algorithm": "sha256"
    },
    {
      "id": "github_release/github.com/bufbuild/buf/v1.51.0/buf-Windows-x86_64.exe",
      "checksum": "BBE19813D02774CF55EC4418567D50E6C8A6DA0AB9CD970B13BC24CC655075D0",
      "algorithm": "sha256"
    },
    {
      "id": "github_release/github.com/cli/cli/v2.69.0/gh_2.69.0_linux_amd64.tar.gz",
      "checksum": "6E3079E1220920EB61B9E8B68093F6E84B6FB0676AC7DA3716689421134C7CFF",
      "algorithm": "sha256"
    },
    {
      "id": "github_release/github.com/cli/cli/v2.69.0/gh_2.69.0_linux_arm64.tar.gz",
      "checksum": "B910B612AD001C2BCE19F1CFAB6C97AF5AFB9038ABB815BBC667920901281216",
      "algorithm": "sha256"
    },
    {
      "id": "github_release/github.com/cli/cli/v2.69.0/gh_2.69.0_macOS_amd64.zip",
      "checksum": "5885E40616DD562681767377A242D82E170781AD91CC0ECEB02F6843121A3FA9",
      "algorithm": "sha256"
    },
    {
      "id": "github_release/github.com/cli/cli/v2.69.0/gh_2.69.0_macOS_arm64.zip",
      "checksum": "CC7E3F36F9F36F52867EA8203C198454DE09130A88E709D95EED89916132B53C",
      "algorithm": "sha256"
    },
    {
      "id": "github_release/github.com/cli/cli/v2.69.0/gh_2.69.0_windows_amd64.zip",
      "checksum": "6BE76F4C73464BF0317630BED2149BE784FB8343D08E6C8472E0B4AAC2A5ABBE",
      "algorithm": "sha256"
    },
    {
      "id": "github_release/github.com/cli/cli/v2.69.0/gh_2.69.0_windows_arm64.zip",
      "checksum": "45CC2EE4E1741719E27FCFA1A751EC1D0408F093D210F8007EEA20C8EA317BD8",
      "algorithm": "sha256"
    },
    {
      "id": "github_release/github.com/dandavison/delta/0.18.2/delta-0.18.2-aarch64-apple-darwin.tar.gz",
      "checksum": "6BA38DCE9F91EE1B9A24AA4AEDE1DB7195258FE176C3F8276AE2D4457D8170A0",
      "algorithm": "sha256"
    },
    {
      "id": "github_release/github.com/dandavison/delta/0.18.2/delta-0.18.2-aarch64-unknown-linux-gnu.tar.gz",
      "checksum": "ADF7674086DAA4582F598F74CE9CAA6B70C1BA8F4A57D2911499B37826B014F9",
      "algorithm": "sha256"
    },
    {
      "id": "github_release/github.com/dandavison/delta/0.18.2/delta-0.18.2-x86_64-apple-darwin.tar.gz",
      "checksum": "E9B5C4A9E73D2119C687E074F0D97F188E30E5FE8AE0E6D455755F74BB5CC0CF",
      "algorithm": "sha256"
    },
    {
      "id": "github_release/github.com/dandavison/delta/0.18.2/delta-0.18.2-x86_64-pc-windows-msvc.zip",
      "checksum": "6EA59864091B4CFCA89D9EE38388FF1A3CCDC8244B6E1CDD5201259DE89B0B06",
      "algorithm": "sha256"
    },
    {
      "id": "github_release/github.com/dandavison/delta/0.18.2/delta-0.18.2-x86_64-unknown-linux-musl.tar.gz",
      "checksum": "B7EA845004762358A00EF9127DD9FD723E333C7E4B9CB1DA220C3909372310EE",
      "algorithm": "sha256"
    },
    {
      "id": "github_release/github.com/denoland/deno/v2.2.6/deno-aarch64-apple-darwin.zip",
      "checksum": "4459182BD23C28958C807F06645E371EC8A34CDDB70A1D99680E75CCA76D6E86",
      "algorithm": "sha256"
    },
    {
      "id": "github_release/github.com/denoland/deno/v2.2.6/deno-aarch64-unknown-linux-gnu.zip",
      "checksum": "6FBB81191C38488DE73F4A8612D856D4EEB45165121DD57C6F68A46DE82D30AA",
      "algorithm": "sha256"
    },
    {
      "id": "github_release/github.com/denoland/deno/v2.2.6/deno-x86_64-apple-darwin.zip",
      "checksum": "85EAA0D3F8E76931CA4B03F3D5BEFCB2AD72942DB2A3233E3ABF2DAB58DB52BC",
      "algorithm": "sha256"
    },
    {
      "id": "github_release/github.com/denoland/deno/v2.2.6/deno-x86_64-pc-windows-msvc.zip",
      "checksum": "E0229E239B4B3FFD356A7731DCAB9E277C7750669C27515C4C22CD21B1C0108D",
      "algorithm": "sha256"
    },
    {
      "id": "github_release/github.com/denoland/deno/v2.2.6/deno-x86_64-unknown-linux-gnu.zip",
      "checksum": "2BC96C49F5CEB5A74ADD43F16381E2A2AB5F509C5A5665C5533A661A4141E650",
      "algorithm": "sha256"
    },
    {
      "id": "github_release/github.com/direnv/direnv/v2.35.0/direnv.darwin-amd64",
      "checksum": "4F9ED9888D22CDDAA54E0B1BB132A90E04703647C2FC318774ACE39E48E66A49",
      "algorithm": "sha256"
    },
    {
      "id": "github_release/github.com/direnv/direnv/v2.35.0/direnv.darwin-arm64",
      "checksum": "EDF7087C1A123F5A77424865A17139FBF776A3A25A2184DA7C2FCA227AD7A704",
      "algorithm": "sha256"
    },
    {
      "id": "github_release/github.com/direnv/direnv/v2.35.0/direnv.linux-amd64",
      "checksum": "55C294F4376397C68B1F659F049FB104DC2ECD0FCB15A15949D7F748E3F70B66",
      "algorithm": "sha256"
    },
    {
      "id": "github_release/github.com/direnv/direnv/v2.35.0/direnv.linux-arm64",
      "checksum": "B7B49853C7C822714A922A53D6DFFDED516F72B9A0324D029975A83662E065C2",
      "algorithm": "sha256"
    },
    {
      "id": "github_release/github.com/direnv/direnv/v2.35.0/direnv.windows-amd64.exe",
      "checksum": "F342C92F3500B71172BA39AD4FAC91774971FBB499985543A558871761282F6D",
      "algorithm": "sha256"
    },
    {
      "id": "github_release/github.com/eza-community/eza/v0.21.0/eza.exe_x86_64-pc-windows-gnu.tar.gz",
      "checksum": "BEBCC98BB02E1C9B33836E0851F4A5084524B272A9DE7901A72234895049DC13",
      "algorithm": "sha256"
    },
    {
      "id": "github_release/github.com/eza-community/eza/v0.21.0/eza_aarch64-unknown-linux-gnu.tar.gz",
      "checksum": "B31A125BB27C807F821ED0593C16EE6E67691E134234FE86021CD5F4F0F5DEEE",
      "algorithm": "sha256"
    },
    {
      "id": "github_release/github.com/eza-community/eza/v0.21.0/eza_x86_64-unknown-linux-musl.tar.gz",
      "checksum": "DDB11B0EEA687CDEA02FE3D8F6AEF98BBCA41580872BE0899E5A34C6031C8406",
      "algorithm": "sha256"
    },
    {
      "id": "github_release/github.com/golangci/golangci-lint/v1.64.8/golangci-lint-1.64.8-darwin-amd64.tar.gz",
      "checksum": "B52AEBB8CB51E00BFD5976099083FBE2C43EF556CEF9C87E58A8AE656E740444",
      "algorithm": "sha256"
    },
    {
      "id": "github_release/github.com/golangci/golangci-lint/v1.64.8/golangci-lint-1.64.8-darwin-arm64.tar.gz",
      "checksum": "70543D21E5B02A94079BE8AA11267A5B060865583E337FE768D39B5D3E2FAF1F",
      "algorithm": "sha256"
    },
    {
      "id": "github_release/github.com/golangci/golangci-lint/v1.64.8/golangci-lint-1.64.8-linux-amd64.tar.gz",
      "checksum": "B6270687AFB143D019F387C791CD2A6F1CB383BE9B3124D241CA11BD3CE2E54E",
      "algorithm": "sha256"
    },
    {
      "id": "github_release/github.com/golangci/golangci-lint/v1.64.8/golangci-lint-1.64.8-linux-arm64.tar.gz",
      "checksum": "A6AB58EBCB1C48572622146CDAEC2956F56871038A54ED1149F1386E287789A5",
      "algorithm": "sha256"
    },
    {
      "id": "github_release/github.com/golangci/golangci-lint/v1.64.8/golangci-lint-1.64.8-windows-amd64.zip",
      "checksum": "54C2ED3A6B4F2F5DA1056FB6E83D6B73B592E06684B65A5999174FABBB251A8F",
      "algorithm": "sha256"
    },
    {
      "id": "github_release/github.com/golangci/golangci-lint/v1.64.8/golangci-lint-1.64.8-windows-arm64.zip",
      "checksum": "24294BC46BC887691C7A43C66448F1DF9203C0A9C15BCB114B6147AA97973505",
      "algorithm": "sha256"
    },
    {
      "id": "github_release/github.com/grafana/jsonnet-language-server/v0.15.0/jsonnet-language-server_0.15.0_darwin_amd64",
      "checksum": "F084464DEE4D6888AF37CF7D71819C95547FF062DED4B67CFFA1D700A29AFB5B",
      "algorithm": "sha256"
    },
    {
      "id": "github_release/github.com/grafana/jsonnet-language-server/v0.15.0/jsonnet-language-server_0.15.0_darwin_arm64",
      "checksum": "85A47A9D1F42B80513858B3FD288CF305D14C00D33A3A9BECF8B234232C6A304",
      "algorithm": "sha256"
    },
    {
      "id": "github_release/github.com/grafana/jsonnet-language-server/v0.15.0/jsonnet-language-server_0.15.0_linux_amd64",
      "checksum": "3A24C762F36E02874EA361B4C54A7744AA860E135B59FD918063941B71DF9F62",
      "algorithm": "sha256"
    },
    {
      "id": "github_release/github.com/grafana/jsonnet-language-server/v0.15.0/jsonnet-language-server_0.15.0_linux_arm64",
      "checksum": "368DD53A8DF7705CA461E5B6681324536C4C017BDD1F1A5AF6BA0CFE3CB59601",
      "algorithm": "sha256"
    },
    {
      "id": "github_release/github.com/grafana/jsonnet-language-server/v0.15.0/jsonnet-language-server_0.15.0_windows_amd64.exe",
      "checksum": "6FC0DF20489AE34DBFF4CE1713A1F896BAF16979BF2BAA875BBBD36B4075FE37",
      "algorithm": "sha256"
    },
    {
      "id": "github_release/github.com/grafana/jsonnet-language-server/v0.15.0/jsonnet-language-server_0.15.0_windows_arm64.exe",
      "checksum": "1A20346F77452124503E6A878C526A95DCFCD80287409141451BEE2E74FE6815",
      "algorithm": "sha256"
    },
    {
      "id": "github_release/github.com/hadolint/hadolint/v2.12.0/hadolint-Darwin-x86_64",
      "checksum": "2A5B7AFCAB91645C39A7CEBEFCD835B865F7488E69BE24567F433DFC3D41CD27",
      "algorithm": "sha256"
    },
    {
      "id": "github_release/github.com/hadolint/hadolint/v2.12.0/hadolint-Linux-arm64",
      "checksum": "5798551BF19F33951881F15EB238F90AEF023F11E7EC7E9F4C37961CB87C5DF6",
      "algorithm": "sha256"
    },
    {
      "id": "github_release/github.com/hadolint/hadolint/v2.12.0/hadolint-Linux-x86_64",
      "checksum": "56DE6D5E5EC427E17B74FA48D51271C7FC0D61244BF5C90E828AAB8362D55010",
      "algorithm": "sha256"
    },
    {
      "id": "github_release/github.com/hadolint/hadolint/v2.12.0/hadolint-Windows-x86_64.exe",
      "checksum": "ED89A156290E15452276B2B4C84EFA688A5183D3B578BFAEC7CFDF986F0632A8",
      "algorithm": "sha256"
    },
    {
      "id": "github_release/github.com/jesseduffield/lazydocker/v0.24.1/lazydocker_0.24.1_Darwin_x86_64.tar.gz",
      "checksum": "7B4C73C7B1B62B9702A701AC0A8A1D8913602173362E8EE96D4FC03EF556AD10",
      "algorithm": "sha256"
    },
    {
      "id": "github_release/github.com/jesseduffield/lazydocker/v0.24.1/lazydocker_0.24.1_Linux_arm64.tar.gz",
      "checksum": "C38E715F2CB56440BEC16E3744005522C1D13C47D2E3730572849DC69CEFD8AE",
      "algorithm": "sha256"
    },
    {
      "id": "github_release/github.com/jesseduffield/lazydocker/v0.24.1/lazydocker_0.24.1_Linux_x86_64.tar.gz",
      "checksum": "461CACF618E1020DFF1D7896248C1C1F2267D5C25FB529755E4B9C43C5D1D4A5",
      "algorithm": "sha256"
    },
    {
      "id": "github_release/github.com/jesseduffield/lazydocker/v0.24.1/lazydocker_0.24.1_Windows_x86_64.zip",
      "checksum": "CC54494D8CD9232D8D64CF4C2D720A045E5B969A716739424702577F55B53CF9",
      "algorithm": "sha256"
    },
    {
      "id": "github_release/github.com/jesseduffield/lazygit/v0.48.0/lazygit_0.48.0_Darwin_arm64.tar.gz",
      "checksum": "A14777516794BA7EDB4AF716F73B908AF9CD4BFE784CBAAC2A7A5028F3F21247",
      "algorithm": "sha256"
    },
    {
      "id": "github_release/github.com/jesseduffield/lazygit/v0.48.0/lazygit_0.48.0_Darwin_x86_64.tar.gz",
      "checksum": "A8C99BDAAFE4392D79356CFADEE74E62B0724DF113E02FDB1F45E1F691B277DF",
      "algorithm": "sha256"
    },
    {
      "id": "github_release/github.com/jesseduffield/lazygit/v0.48.0/lazygit_0.48.0_Linux_arm64.tar.gz",
      "checksum": "37150EC77BD42D92B7DC96F05FCA5F1CD310551936E32556011AC145CCD9D62B",
      "algorithm": "sha256"
    },
    {
      "id": "github_release/github.com/jesseduffield/lazygit/v0.48.0/lazygit_0.48.0_Linux_x86_64.tar.gz",
      "checksum": "291722C643A10805DE3BD7B58F51D5275878269AEADB046709708F8683F558D7",
      "algorithm": "sha256"
    },
    {
      "id": "github_release/github.com/jesseduffield/lazygit/v0.48.0/lazygit_0.48.0_Windows_x86_64.zip",
      "checksum": "26BA0970FC399075826F8612DFDA39FE9E25114337264A0DC810C09CD25A758C",
      "algorithm": "sha256"
    },
    {
      "id": "github_release/github.com/junegunn/fzf/v0.61.0/fzf-0.61.0-darwin_amd64.tar.gz",
      "checksum": "1C7DA66FC557D383220D0CCC5E37D5913C96B7AB326C1A4E557BBE7C08319767",
      "algorithm": "sha256"
    },
    {
      "id": "github_release/github.com/junegunn/fzf/v0.61.0/fzf-0.61.0-darwin_arm64.tar.gz",
      "checksum": "D8230BB1A38817B7B7DC13100F9EF951FDC216E60DF04E6C4015EE6ACEA54AEB",
      "algorithm": "sha256"
    },
    {
      "id": "github_release/github.com/junegunn/fzf/v0.61.0/fzf-0.61.0-linux_amd64.tar.gz",
      "checksum": "69767835A69F0EAEF03D4EA4117B32197382EBB59CAE358EA22F08B46C33FA50",
      "algorithm": "sha256"
    },
    {
      "id": "github_release/github.com/junegunn/fzf/v0.61.0/fzf-0.61.0-linux_arm64.tar.gz",
      "checksum": "760F4F62C30AF0F722430AF099C40AF191B3FE5A55B8F850926DAC406F6BF9FE",
      "algorithm": "sha256"
    },
    {
      "id": "github_release/github.com/junegunn/fzf/v0.61.0/fzf-0.61.0-windows_amd64.zip",
      "checksum": "812E272E2038E969A370FD96EBE604D5ED4D29F465AE60412CFB3B768E0A1CAF",
      "algorithm": "sha256"
    },
    {
      "id": "github_release/github.com/junegunn/fzf/v0.61.0/fzf-0.61.0-windows_arm64.zip",
      "checksum": "B75AEEEC398BB8F7E8744B4B0EB76483B53B8DFC245CE665612872A25FFFA2AF",
      "algorithm": "sha256"
    },
    {
      "id": "github_release/github.com/mvdan/sh/v3.11.0/shfmt_v3.11.0_darwin_amd64",
      "checksum": "810A76CB7C78351E021C8025F344B12149D8426CE51609A179AF68109ED5698E",
      "algorithm": "sha256"
    },
    {
      "id": "github_release/github.com/mvdan/sh/v3.11.0/shfmt_v3.11.0_darwin_arm64",
      "checksum": "AF206D234DFF5D05D9AC355529B2B33A7A78E13FAB9B59DB777746AAB3E72530",
      "algorithm": "sha256"
    },
    {
      "id": "github_release/github.com/mvdan/sh/v3.11.0/shfmt_v3.11.0_linux_amd64",
      "checksum": "1904EC6BAC715C1D05CD7F6612EEC8F67A625C3749CB327E5BFB4127D09035FF",
      "algorithm": "sha256"
    },
    {
      "id": "github_release/github.com/mvdan/sh/v3.11.0/shfmt_v3.11.0_linux_arm64",
      "checksum": "B3976121710FD4B12BF641B0A7FB2686DA598FB0DA9F148C641B61B54CFA3407",
      "algorithm": "sha256"
    },
    {
      "id": "github_release/github.com/mvdan/sh/v3.11.0/shfmt_v3.11.0_windows_amd64.exe",
      "checksum": "D11A0880588304496065110CB67CE2375CFCD5433E76DEC505CE1FA21ADF47CC",
      "algorithm": "sha256"
    },
    {
      "id": "github_release/github.com/nametake/golangci-lint-langserver/v0.0.10/golangci-lint-langserver_Darwin_arm64.tar.gz",
      "checksum": "6F5D60253247751556B0477D87627F266ECC0E6F9138B7582EA7C0894A9A596B",
      "algorithm": "sha256"
    },
    {
      "id": "github_release/github.com/nametake/golangci-lint-langserver/v0.0.10/golangci-lint-langserver_Darwin_x86_64.tar.gz",
      "checksum": "404C240014FE6752BD4014ECCE04A1087BBECC4ED1E311AFF8CF4E8F0D13996D",
      "algorithm": "sha256"
    },
    {
      "id": "github_release/github.com/nametake/golangci-lint-langserver/v0.0.10/golangci-lint-langserver_Linux_arm64.tar.gz",
      "checksum": "B54CF80A0C7B86D2D9B21371AC45A0C9157542D832284A131C0666C7A2D15768",
      "algorithm": "sha256"
    },
    {
      "id": "github_release/github.com/nametake/golangci-lint-langserver/v0.0.10/golangci-lint-langserver_Linux_x86_64.tar.gz",
      "checksum": "5C9D0BE947D9E61B0DF241D90E13454A38B928F011B45044C5F11D97E637CAF9",
      "algorithm": "sha256"
    },
    {
      "id": "github_release/github.com/nametake/golangci-lint-langserver/v0.0.10/golangci-lint-langserver_Windows_arm64.zip",
      "checksum": "FC738BBA58F1E944E45DEF1F6B6CD17FC0886070AE63D07C2B771C70E6C398D3",
      "algorithm": "sha256"
    },
    {
      "id": "github_release/github.com/nametake/golangci-lint-langserver/v0.0.10/golangci-lint-langserver_Windows_x86_64.zip",
      "checksum": "4E1B08C716992706FBD979EFC069ED7E52B2A45DD7D83FB0143BEEBDAB5F1077",
      "algorithm": "sha256"
    },
    {
      "id": "github_release/github.com/neovim/neovim/v0.11.0/nvim-linux-arm64.tar.gz",
      "checksum": "6959583F45042DA20E0A082DC65108725629A4739AB91246C678FD084ECAF50E",
      "algorithm": "sha256"
    },
    {
      "id": "github_release/github.com/neovim/neovim/v0.11.0/nvim-linux-x86_64.tar.gz",
      "checksum": "FE0A5BC79E64C5E4D9F844CD96157EBD3919EF1343B329E9EBC3F455924CC7D6",
      "algorithm": "sha256"
    },
    {
      "id": "github_release/github.com/neovim/neovim/v0.11.0/nvim-macos-arm64.tar.gz",
      "checksum": "20055D322E80194350EE0E47F1BA5A8016D1CDBE7E283D62F882F640326E18A7",
      "algorithm": "sha256"
    },
    {
      "id": "github_release/github.com/neovim/neovim/v0.11.0/nvim-macos-x86_64.tar.gz",
      "checksum": "30DC06F0E5B945BFF4F3A1994608BFF912CA4EC249774063EB9D8B0CE30018E5",
      "algorithm": "sha256"
    },
    {
      "id": "github_release/github.com/neovim/neovim/v0.11.0/nvim-win64.zip",
      "checksum": "00EA1A0FD3252A883974A3411159087196924F214000583257188B205D173A23",
      "algorithm": "sha256"
    },
    {
      "id": "github_release/github.com/pnpm/pnpm/v10.7.1/pnpm-linux-arm64",
      "checksum": "679AE00C18E30E68ED921F39F23B27905F2239CAA51B01811262D7F2D2D71C7D",
      "algorithm": "sha256"
    },
    {
      "id": "github_release/github.com/pnpm/pnpm/v10.7.1/pnpm-linux-x64",
      "checksum": "9EF305B7BE447C9D6899B9B4618B7A788E5EB09F38398196D648909CBE12DA72",
      "algorithm": "sha256"
    },
    {
      "id": "github_release/github.com/pnpm/pnpm/v10.7.1/pnpm-macos-arm64",
      "checksum": "C137C407BE6E3C71BE0567A6936C6AB2C9043FB5D0E69B97C9E47307E010545D",
      "algorithm": "sha256"
    },
    {
      "id": "github_release/github.com/pnpm/pnpm/v10.7.1/pnpm-macos-x64",
      "checksum": "FD05D06CB93FADA85B7D7CC7551FF095AAE3A1AB433544C9A0CC83A5EED0E972",
      "algorithm": "sha256"
    },
    {
      "id": "github_release/github.com/pnpm/pnpm/v10.7.1/pnpm-win-x64.exe",
      "checksum": "4281075ED211C027454A1643E5A0C3E12DBF1710DFE7EE4FA7A024417ED2DB46",
      "algorithm": "sha256"
    },
    {
      "id": "github_release/github.com/rhysd/actionlint/v1.7.7/actionlint_1.7.7_darwin_amd64.tar.gz",
      "checksum": "28E5DE5A05FC558474F638323D736D822FFF183D2D492F0AECB2B73CC44584F5",
      "algorithm": "sha256"
    },
    {
      "id": "github_release/github.com/rhysd/actionlint/v1.7.7/actionlint_1.7.7_darwin_arm64.tar.gz",
      "checksum": "2693315B9093AEACB4EBD91A993FEA54FC215057BF0DA2659056B4BC033873DB",
      "algorithm": "sha256"
    },
    {
      "id": "github_release/github.com/rhysd/actionlint/v1.7.7/actionlint_1.7.7_linux_amd64.tar.gz",
      "checksum": "023070A287CD8CCCD71515FEDC843F1985BF96C436B7EFFAECCE67290E7E0757",
      "algorithm": "sha256"
    },
    {
      "id": "github_release/github.com/rhysd/actionlint/v1.7.7/actionlint_1.7.7_linux_arm64.tar.gz",
      "checksum": "401942F9C24ED71E4FE71B76C7D638F66D8633575C4016EFD2977CE7C28317D0",
      "algorithm": "sha256"
    },
    {
      "id": "github_release/github.com/rhysd/actionlint/v1.7.7/actionlint_1.7.7_windows_amd64.zip",
      "checksum": "7F12F1801BCA3D480D67AAF7774F4C2A6359A3CA8EEBE382C95C10C9704AA731",
      "algorithm": "sha256"
    },
    {
      "id": "github_release/github.com/rhysd/actionlint/v1.7.7/actionlint_1.7.7_windows_arm64.zip",
      "checksum": "76E9514CFAC18E5677AA04F3A89873C981F16A2F2353BB97372A86CD09B1F5A8",
      "algorithm": "sha256"
    },
    {
      "id": "github_release/github.com/sharkdp/bat/v0.25.0/bat-v0.25.0-aarch64-apple-darwin.tar.gz",
      "checksum": "B3ED5A7515545445881F1036F0CC1B708C2B86CBCE01C1B4033F38E0CFCC7B3C",
      "algorithm": "sha256"
    },
    {
      "id": "github_release/github.com/sharkdp/bat/v0.25.0/bat-v0.25.0-aarch64-unknown-linux-musl.tar.gz",
      "checksum": "EE0F12CF6006A79CF4CCF75D2DDCF9F6BA124644503244B1AF909C2F72A2A9F7",
      "algorithm": "sha256"
    },
    {
      "id": "github_release/github.com/sharkdp/bat/v0.25.0/bat-v0.25.0-x86_64-apple-darwin.tar.gz",
      "checksum": "B974AA834B6B65610090AED2BC7310D11C6F500105696D23A130AEE24FD8380F",
      "algorithm": "sha256"
    },
    {
      "id": "github_release/github.com/sharkdp/bat/v0.25.0/bat-v0.25.0-x86_64-pc-windows-msvc.zip",
      "checksum": "1D5CED071BA9C765E16F4065877C178CEFCFD2FE9581E9DDC92AF265B73991BD",
      "algorithm": "sha256"
    },
    {
      "id": "github_release/github.com/sharkdp/bat/v0.25.0/bat-v0.25.0-x86_64-unknown-linux-musl.tar.gz",
      "checksum": "93F47D76ABE328C402EF712E9AC92AA6D5BC84D5ADCBCAF0BBC5665E5275A941",
      "algorithm": "sha256"
    },
    {
      "id": "github_release/github.com/sharkdp/fd/v10.2.0/fd-v10.2.0-aarch64-apple-darwin.tar.gz",
      "checksum": "AE6327BA8C9A487CD63EDD8BDDD97DA0207887A66D61E067DFE80C1430C5AE36",
      "algorithm": "sha256"
    },
    {
      "id": "github_release/github.com/sharkdp/fd/v10.2.0/fd-v10.2.0-aarch64-unknown-linux-musl.tar.gz",
      "checksum": "4E8E596646D047D904F2C5CA74B39DCCC69978B6E1FB101094E534B0B59C1BB0",
      "algorithm": "sha256"
    },
    {
      "id": "github_release/github.com/sharkdp/fd/v10.2.0/fd-v10.2.0-x86_64-apple-darwin.tar.gz",
      "checksum": "991A648A58870230AF9547C1AE33E72CB5C5199A622FE5E540E162D6DBA82D48",
      "algorithm": "sha256"
    },
    {
      "id": "github_release/github.com/sharkdp/fd/v10.2.0/fd-v10.2.0-x86_64-pc-windows-msvc.zip",
      "checksum": "92AC9E6B0A0C6ECDAB638FFE210DC786403FFF4C66373604CF70DF27BE45E4FE",
      "algorithm": "sha256"
    },
    {
      "id": "github_release/github.com/sharkdp/fd/v10.2.0/fd-v10.2.0-x86_64-unknown-linux-musl.tar.gz",
      "checksum": "D9BFA25EC28624545C222992E1B00673B7C9CA5EB15393C40369F10B28F9C932",
      "algorithm": "sha256"
    },
    {
      "id": "github_release/github.com/starship/starship/v1.22.1/starship-aarch64-apple-darwin.tar.gz",
      "checksum": "B73B2EF7995EAF07D18A806C3D3ADDABA7797D1FAB2DACEB875944BF038B97A9",
      "algorithm": "sha256"
    },
    {
      "id": "github_release/github.com/starship/starship/v1.22.1/starship-aarch64-pc-windows-msvc.zip",
      "checksum": "E70380CA76C9A83A7DED88C1D2EDCF84EE79222B7274B8C8C6D74BC8A9B7B0D1",
      "algorithm": "sha256"
    },
    {
      "id": "github_release/github.com/starship/starship/v1.22.1/starship-aarch64-unknown-linux-musl.tar.gz",
      "checksum": "B82EDD21060F3ED112460442C48A3A9545C8DBF3B564154441F4E6B58EACC387",
      "algorithm": "sha256"
    },
    {
      "id": "github_release/github.com/starship/starship/v1.22.1/starship-x86_64-apple-darwin.tar.gz",
      "checksum": "38F13F3EC091A900996F47A74E3F31F8067DC3D6FD59D6BC179E4CEB853EBA91",
      "algorithm": "sha256"
    },
    {
      "id": "github_release/github.com/starship/starship/v1.22.1/starship-x86_64-pc-windows-msvc.zip",
      "checksum": "D7E7252C992C65130DAEBE3FB7A087A273F63DC54AF7883E5DFC4616D034871A",
      "algorithm": "sha256"
    },
    {
      "id": "github_release/github.com/starship/starship/v1.22.1/starship-x86_64-unknown-linux-musl.tar.gz",
      "checksum": "62C91B5ECC7F8C8C6EA7FFEA42A98BD2E6A2D29DAF61562FAC04DAECE18A6461",
      "algorithm": "sha256"
    },
    {
      "id": "github_release/github.com/stripe/stripe-cli/v1.26.1/stripe_1.26.1_linux_arm64.tar.gz",
      "checksum": "C11A495D98881C4B5FACA580876230F53CD19FD8CC0C5926D36E101CA54170DF",
      "algorithm": "sha256"
    },
    {
      "id": "github_release/github.com/stripe/stripe-cli/v1.26.1/stripe_1.26.1_linux_x86_64.tar.gz",
      "checksum": "4C1DCB1AA59556F9A5457C3188121349CB5732B4DAFE689845AAF47D86FFF8D5",
      "algorithm": "sha256"
    },
    {
      "id": "github_release/github.com/stripe/stripe-cli/v1.26.1/stripe_1.26.1_mac-os_arm64.tar.gz",
      "checksum": "5C5115BA47FB2EE3F33DC03028739956170C987E475F29ED166B0F8A3F2F7C71",
      "algorithm": "sha256"
    },
    {
      "id": "github_release/github.com/stripe/stripe-cli/v1.26.1/stripe_1.26.1_mac-os_x86_64.tar.gz",
      "checksum": "29F5AA4222547E00FE60EF00FCDBDBAF3880DFFC870A60F4EFCC0334D6D33374",
      "algorithm": "sha256"
    },
    {
      "id": "github_release/github.com/stripe/stripe-cli/v1.26.1/stripe_1.26.1_windows_x86_64.zip",
      "checksum": "B155835BD339D9390A25A0319D86AEC04CEC3E579B24625FC150F5340396DCD0",
      "algorithm": "sha256"
    },
    {
      "id": "github_release/github.com/x-motemen/ghq/v1.8.0/ghq_darwin_amd64.zip",
      "checksum": "742A64C85B7C01A1399AE286E886CFFC4649EE38891FB01CD32F31394610EA80",
      "algorithm": "sha256"
    },
    {
      "id": "github_release/github.com/x-motemen/ghq/v1.8.0/ghq_darwin_arm64.zip",
      "checksum": "0399A4DCDDEEB9E76F7F9EEB8015F91A6F093B04C14D3EB87EB563E5D94F9B0A",
      "algorithm": "sha256"
    },
    {
      "id": "github_release/github.com/x-motemen/ghq/v1.8.0/ghq_linux_amd64.zip",
      "checksum": "AD0EC7B2F52312DCA85F35B5C9E88A77447C2C71BABBD9DFEB569AB369B8E55F",
      "algorithm": "sha256"
    },
    {
      "id": "github_release/github.com/x-motemen/ghq/v1.8.0/ghq_linux_arm64.zip",
      "checksum": "982A8D0F832664B6D54A0C4089198414B97DCB33E5AED7897C5C0F0FC10E6806",
      "algorithm": "sha256"
    },
    {
      "id": "github_release/github.com/x-motemen/ghq/v1.8.0/ghq_windows_amd64.zip",
      "checksum": "F609538DD0A46987EEE933FFF8A1607DFB788DF7C396F2282821AE52BD3210BD",
      "algorithm": "sha256"
    },
    {
      "id": "github_release/github.com/x-motemen/ghq/v1.8.0/ghq_windows_arm64.zip",
      "checksum": "03E329E679B10A1B1A2C28A9BCB6D90AE9A39E273C0E8923071ABF8F72DB1C85",
      "algorithm": "sha256"
    },
    {
      "id": "http/awscli.amazonaws.com/AWSCLIV2-2.25.10.pkg",
      "checksum": "1254B332021B8A85F7CE08FD930546D995873F2EAEBA970BFEE370C05057FE20",
      "algorithm": "sha256"
    },
    {
      "id": "http/awscli.amazonaws.com/awscli-exe-linux-aarch64-2.25.10.zip",
      "checksum": "1BC4606011BF99EE214E32D6A627BDFCEC78CE2F54ED8143C0B780A995563292",
      "algorithm": "sha256"
    },
    {
      "id": "http/awscli.amazonaws.com/awscli-exe-linux-x86_64-2.25.10.zip",
      "checksum": "7D9A50C4CDE3CD98084012C980B34D5CD4A840E79F487C6FAF5DAD9C8A72AA70",
      "algorithm": "sha256"
    },
    {
      "id": "http/golang.org/dl/go1.24.2.darwin-amd64.tar.gz",
      "checksum": "238D9C065D09FF6AF229D2E3B8B5E85E688318D69F4006FB85A96E41C216EA83",
      "algorithm": "sha256"
    },
    {
      "id": "http/golang.org/dl/go1.24.2.darwin-arm64.tar.gz",
      "checksum": "B70F8B3C5B4CCB0AD4FFA5EE91CD38075DF20FDBD953A1DAEDD47F50FBCFF47A",
      "algorithm": "sha256"
    },
    {
      "id": "http/golang.org/dl/go1.24.2.linux-amd64.tar.gz",
      "checksum": "68097BD680839CBC9D464A0EDCE4F7C333975E27A90246890E9F1078C7E702AD",
      "algorithm": "sha256"
    },
    {
      "id": "http/golang.org/dl/go1.24.2.linux-arm64.tar.gz",
      "checksum": "756274EA4B68FA5535EB9FE2559889287D725A8DA63C6AAE4D5F23778C229F4B",
      "algorithm": "sha256"
    },
    {
      "id": "http/golang.org/dl/go1.24.2.windows-amd64.zip",
      "checksum": "29C553AABEE0743E2FFA3E9FA0CDA00EF3B3CC4FF0BC92007F31F80FD69892E1",
      "algorithm": "sha256"
    },
    {
      "id": "http/golang.org/dl/go1.24.2.windows-arm64.zip",
      "checksum": "AB267F7F9A3366D48D7664BE9E627CE3E63273231430CCE5F7783FB910F14148",
      "algorithm": "sha256"
    },
    {
      "id": "registries/github_content/github.com/aquaproj/aqua-registry/v4.336.0/registry.yaml",
      "checksum": "A3C5802FB2B19BFCC2C4FD77A563547E9F76D179643234DA0EE8441A4D753FBAE2E16C87D50FC7F228773D8D359E2E61D5440523C121CCDACF13FC9362FC7673",
      "algorithm": "sha512"
    }
  ]
}
